{
"meta":{"test_sets":[],"test_metrics":[],"learn_metrics":[{"best_value":"Min","name":"RMSE"}],"launch_mode":"Train","parameters":"","iteration_count":1000,"learn_sets":["learn"],"name":"experiment"},
"iterations":[
{"learn":[5.359264039],"iteration":0,"passed_time":0.01195371352,"remaining_time":11.94175981},
{"learn":[5.173424367],"iteration":1,"passed_time":0.02295372378,"remaining_time":11.45390817},
{"learn":[4.995140452],"iteration":2,"passed_time":0.03386791117,"remaining_time":11.25543581},
{"learn":[4.841024718],"iteration":3,"passed_time":0.04500679643,"remaining_time":11.20669231},
{"learn":[4.695028204],"iteration":4,"passed_time":0.05724657548,"remaining_time":11.39206852},
{"learn":[4.569606062],"iteration":5,"passed_time":0.0680670147,"remaining_time":11.27643543},
{"learn":[4.451182143],"iteration":6,"passed_time":0.07892046782,"remaining_time":11.19543208},
{"learn":[4.351244105],"iteration":7,"passed_time":0.09003072025,"remaining_time":11.16380931},
{"learn":[4.257924941],"iteration":8,"passed_time":0.1008016186,"remaining_time":11.09937822},
{"learn":[4.173755693],"iteration":9,"passed_time":0.1118616231,"remaining_time":11.07430069},
{"learn":[4.093097344],"iteration":10,"passed_time":0.122574787,"remaining_time":11.02058767},
{"learn":[4.01428604],"iteration":11,"passed_time":0.1338622867,"remaining_time":11.02132827},
{"learn":[3.942084738],"iteration":12,"passed_time":0.1453689312,"remaining_time":11.03685654},
{"learn":[3.877283329],"iteration":13,"passed_time":0.1567769447,"remaining_time":11.04157625},
{"learn":[3.821926998],"iteration":14,"passed_time":0.1680771413,"remaining_time":11.03706561},
{"learn":[3.767674524],"iteration":15,"passed_time":0.1788892809,"remaining_time":11.00169078},
{"learn":[3.720559809],"iteration":16,"passed_time":0.189378689,"remaining_time":10.9505442},
{"learn":[3.678604825],"iteration":17,"passed_time":0.2003382351,"remaining_time":10.92956372},
{"learn":[3.636501936],"iteration":18,"passed_time":0.2108333496,"remaining_time":10.88565874},
{"learn":[3.59773155],"iteration":19,"passed_time":0.2215968211,"remaining_time":10.85824423},
{"learn":[3.562452212],"iteration":20,"passed_time":0.2319581444,"remaining_time":10.81366778},
{"learn":[3.528402303],"iteration":21,"passed_time":0.2419268254,"remaining_time":10.75474705},
{"learn":[3.498573062],"iteration":22,"passed_time":0.2526999221,"remaining_time":10.73425321},
{"learn":[3.470346246],"iteration":23,"passed_time":0.2632358952,"remaining_time":10.7049264},
{"learn":[3.445697889],"iteration":24,"passed_time":0.273579962,"remaining_time":10.66961852},
{"learn":[3.419436971],"iteration":25,"passed_time":0.2837619265,"remaining_time":10.63015832},
{"learn":[3.394736143],"iteration":26,"passed_time":0.2946237072,"remaining_time":10.61736545},
{"learn":[3.373384287],"iteration":27,"passed_time":0.3053948458,"remaining_time":10.60156393},
{"learn":[3.352936338],"iteration":28,"passed_time":0.3161639563,"remaining_time":10.58604143},
{"learn":[3.335567707],"iteration":29,"passed_time":0.3259371827,"remaining_time":10.53863557},
{"learn":[3.317455761],"iteration":30,"passed_time":0.3359629434,"remaining_time":10.50155136},
{"learn":[3.301663657],"iteration":31,"passed_time":0.3460352072,"remaining_time":10.46756502},
{"learn":[3.286682046],"iteration":32,"passed_time":0.3564677884,"remaining_time":10.4455864},
{"learn":[3.272244018],"iteration":33,"passed_time":0.3666598892,"remaining_time":10.4174545},
{"learn":[3.259965137],"iteration":34,"passed_time":0.3766336924,"remaining_time":10.38432895},
{"learn":[3.247383549],"iteration":35,"passed_time":0.3872618489,"remaining_time":10.37001173},
{"learn":[3.235327677],"iteration":36,"passed_time":0.397023264,"remaining_time":10.33333522},
{"learn":[3.225991815],"iteration":37,"passed_time":0.4071138192,"remaining_time":10.30640774},
{"learn":[3.215758528],"iteration":38,"passed_time":0.4174964479,"remaining_time":10.28754068},
{"learn":[3.205902245],"iteration":39,"passed_time":0.4276412226,"remaining_time":10.26338934},
{"learn":[3.196443656],"iteration":40,"passed_time":0.4384819574,"remaining_time":10.25619993},
{"learn":[3.187675872],"iteration":41,"passed_time":0.4492247175,"remaining_time":10.24660189},
{"learn":[3.180053839],"iteration":42,"passed_time":0.4607383084,"remaining_time":10.25410607},
{"learn":[3.172197018],"iteration":43,"passed_time":0.4716173114,"remaining_time":10.24695795},
{"learn":[3.165197423],"iteration":44,"passed_time":0.4816286676,"remaining_time":10.22123061},
{"learn":[3.158923757],"iteration":45,"passed_time":0.4919411431,"remaining_time":10.20243153},
{"learn":[3.152702483],"iteration":46,"passed_time":0.5022644522,"remaining_time":10.18421325},
{"learn":[3.146791676],"iteration":47,"passed_time":0.5123135196,"remaining_time":10.16088481},
{"learn":[3.141807144],"iteration":48,"passed_time":0.5229810724,"remaining_time":10.15010204},
{"learn":[3.136294243],"iteration":49,"passed_time":0.5334602524,"remaining_time":10.13574479},
{"learn":[3.131111646],"iteration":50,"passed_time":0.5436640149,"remaining_time":10.11641471},
{"learn":[3.126199579],"iteration":51,"passed_time":0.5547934402,"remaining_time":10.11431118},
{"learn":[3.12258453],"iteration":52,"passed_time":0.5652167976,"remaining_time":10.09925108},
{"learn":[3.118238051],"iteration":53,"passed_time":0.57572846,"remaining_time":10.08590969},
{"learn":[3.113372415],"iteration":54,"passed_time":0.5867158559,"remaining_time":10.08084516},
{"learn":[3.109228926],"iteration":55,"passed_time":0.5970718535,"remaining_time":10.06492553},
{"learn":[3.101053074],"iteration":56,"passed_time":0.6073211899,"remaining_time":10.04743653},
{"learn":[3.094345325],"iteration":57,"passed_time":0.6172012738,"remaining_time":10.0242},
{"learn":[3.08909525],"iteration":58,"passed_time":0.6271237053,"remaining_time":10.00209164},
{"learn":[3.081419916],"iteration":59,"passed_time":0.637430965,"remaining_time":9.986418451},
{"learn":[3.077356676],"iteration":60,"passed_time":0.6480861362,"remaining_time":9.976276752},
{"learn":[3.072954308],"iteration":61,"passed_time":0.6579078556,"remaining_time":9.95350917},
{"learn":[3.067137078],"iteration":62,"passed_time":0.6689104563,"remaining_time":9.948715833},
{"learn":[3.063147957],"iteration":63,"passed_time":0.6796549118,"remaining_time":9.939953086},
{"learn":[3.058647882],"iteration":64,"passed_time":0.6899458714,"remaining_time":9.924605996},
{"learn":[3.055345893],"iteration":65,"passed_time":0.7003740969,"remaining_time":9.911354645},
{"learn":[3.051995333],"iteration":66,"passed_time":0.7106032376,"remaining_time":9.895415234},
{"learn":[3.049223884],"iteration":67,"passed_time":0.7209003372,"remaining_time":9.880575209},
{"learn":[3.042012791],"iteration":68,"passed_time":0.7316210495,"remaining_time":9.871582566},
{"learn":[3.035317299],"iteration":69,"passed_time":0.7420272038,"remaining_time":9.858361422},
{"learn":[3.03156408],"iteration":70,"passed_time":0.7518660615,"remaining_time":9.837796776},
{"learn":[3.028287458],"iteration":71,"passed_time":0.7624445367,"remaining_time":9.827062917},
{"learn":[3.024925094],"iteration":72,"passed_time":0.7726832981,"remaining_time":9.812019415},
{"learn":[3.02158086],"iteration":73,"passed_time":0.7830013922,"remaining_time":9.798098502},
{"learn":[3.01874125],"iteration":74,"passed_time":0.7936246993,"remaining_time":9.788037958},
{"learn":[3.012739345],"iteration":75,"passed_time":0.8040165623,"remaining_time":9.775148731},
{"learn":[3.007975367],"iteration":76,"passed_time":0.8144674833,"remaining_time":9.7630323},
{"learn":[3.004998602],"iteration":77,"passed_time":0.8245925323,"remaining_time":9.747106599},
{"learn":[3.000644508],"iteration":78,"passed_time":0.8347713386,"remaining_time":9.731954466},
{"learn":[2.99509591],"iteration":79,"passed_time":0.844817097,"remaining_time":9.715396616},
{"learn":[2.991863473],"iteration":80,"passed_time":0.855116576,"remaining_time":9.701878189},
{"learn":[2.989776912],"iteration":81,"passed_time":0.8657680166,"remaining_time":9.692378528},
{"learn":[2.98721897],"iteration":82,"passed_time":0.875931038,"remaining_time":9.677454962},
{"learn":[2.984596946],"iteration":83,"passed_time":0.8864940813,"remaining_time":9.667006886},
{"learn":[2.981385008],"iteration":84,"passed_time":0.896372275,"remaining_time":9.649183902},
{"learn":[2.976481496],"iteration":85,"passed_time":0.9065169828,"remaining_time":9.634378166},
{"learn":[2.972423315],"iteration":86,"passed_time":0.9168261406,"remaining_time":9.62140536},
{"learn":[2.968706477],"iteration":87,"passed_time":0.9269348351,"remaining_time":9.606415563},
{"learn":[2.966171721],"iteration":88,"passed_time":0.938299253,"remaining_time":9.604388983},
{"learn":[2.963727605],"iteration":89,"passed_time":0.9495305528,"remaining_time":9.600808923},
{"learn":[2.960902061],"iteration":90,"passed_time":0.9598855146,"remaining_time":9.588306954},
{"learn":[2.958610823],"iteration":91,"passed_time":0.9705650329,"remaining_time":9.57905489},
{"learn":[2.956340015],"iteration":92,"passed_time":0.9808369134,"remaining_time":9.565796564},
{"learn":[2.954549153],"iteration":93,"passed_time":0.9913596325,"remaining_time":9.555019437},
{"learn":[2.950221857],"iteration":94,"passed_time":1.001602466,"remaining_time":9.541581385},
{"learn":[2.946079934],"iteration":95,"passed_time":1.012361095,"remaining_time":9.533066981},
{"learn":[2.942686849],"iteration":96,"passed_time":1.022560822,"remaining_time":9.519303321},
{"learn":[2.940578342],"iteration":97,"passed_time":1.032960527,"remaining_time":9.507453018},
{"learn":[2.938150451],"iteration":98,"passed_time":1.043080469,"remaining_time":9.493085882},
{"learn":[2.935376444],"iteration":99,"passed_time":1.05380503,"remaining_time":9.484245273},
{"learn":[2.933471301],"iteration":100,"passed_time":1.063919677,"remaining_time":9.469938509},
{"learn":[2.931168739],"iteration":101,"passed_time":1.074156222,"remaining_time":9.456787129},
{"learn":[2.929641246],"iteration":102,"passed_time":1.08442032,"remaining_time":9.443932301},
{"learn":[2.928484057],"iteration":103,"passed_time":1.093912184,"remaining_time":9.424474197},
{"learn":[2.926623959],"iteration":104,"passed_time":1.104383809,"remaining_time":9.413557227},
{"learn":[2.922913382],"iteration":105,"passed_time":1.114730536,"remaining_time":9.401595276},
{"learn":[2.921103653],"iteration":106,"passed_time":1.125438794,"remaining_time":9.392680777},
{"learn":[2.919303412],"iteration":107,"passed_time":1.135385156,"remaining_time":9.377440364},
{"learn":[2.917611548],"iteration":108,"passed_time":1.146139931,"remaining_time":9.368905308},
{"learn":[2.915499382],"iteration":109,"passed_time":1.156416325,"remaining_time":9.356459354},
{"learn":[2.91388822],"iteration":110,"passed_time":1.167672914,"remaining_time":9.351902888},
{"learn":[2.911899793],"iteration":111,"passed_time":1.177592292,"remaining_time":9.3366246},
{"learn":[2.910124781],"iteration":112,"passed_time":1.187888251,"remaining_time":9.324397158},
{"learn":[2.906778266],"iteration":113,"passed_time":1.198360404,"remaining_time":9.313572962},
{"learn":[2.904181209],"iteration":114,"passed_time":1.209298779,"remaining_time":9.306342777},
{"learn":[2.903065429],"iteration":115,"passed_time":1.22024327,"remaining_time":9.299095267},
{"learn":[2.900698861],"iteration":116,"passed_time":1.230546534,"remaining_time":9.286945208},
{"learn":[2.898704246],"iteration":117,"passed_time":1.24100656,"remaining_time":9.275998182},
{"learn":[2.897118813],"iteration":118,"passed_time":1.251372755,"remaining_time":9.264364684},
{"learn":[2.894616007],"iteration":119,"passed_time":1.26182222,"remaining_time":9.253362945},
{"learn":[2.892950588],"iteration":120,"passed_time":1.27224849,"remaining_time":9.242201841},
{"learn":[2.889772976],"iteration":121,"passed_time":1.282450725,"remaining_time":9.229440464},
{"learn":[2.887584579],"iteration":122,"passed_time":1.293083435,"remaining_time":9.219790019},
{"learn":[2.886193256],"iteration":123,"passed_time":1.303085518,"remaining_time":9.205668658},
{"learn":[2.884258918],"iteration":124,"passed_time":1.313012961,"remaining_time":9.191090726},
{"learn":[2.882416466],"iteration":125,"passed_time":1.322895826,"remaining_time":9.176277397},
{"learn":[2.880027461],"iteration":126,"passed_time":1.333303551,"remaining_time":9.165149606},
{"learn":[2.878971693],"iteration":127,"passed_time":1.343839567,"remaining_time":9.154907053},
{"learn":[2.875933287],"iteration":128,"passed_time":1.354105911,"remaining_time":9.142839135},
{"learn":[2.873557122],"iteration":129,"passed_time":1.364202577,"remaining_time":9.129663399},
{"learn":[2.871622041],"iteration":130,"passed_time":1.374233463,"remaining_time":9.116098314},
{"learn":[2.869345455],"iteration":131,"passed_time":1.384422106,"remaining_time":9.103624151},
{"learn":[2.867195854],"iteration":132,"passed_time":1.394354903,"remaining_time":9.089516549},
{"learn":[2.864129813],"iteration":133,"passed_time":1.40448221,"remaining_time":9.076728314},
{"learn":[2.861986144],"iteration":134,"passed_time":1.414408781,"remaining_time":9.062693303},
{"learn":[2.860919575],"iteration":135,"passed_time":1.424510071,"remaining_time":9.049828684},
{"learn":[2.858239475],"iteration":136,"passed_time":1.434646326,"remaining_time":9.037224664},
{"learn":[2.856036423],"iteration":137,"passed_time":1.444847506,"remaining_time":9.025061955},
{"learn":[2.853852202],"iteration":138,"passed_time":1.455040625,"remaining_time":9.012877543},
{"learn":[2.851084022],"iteration":139,"passed_time":1.465348519,"remaining_time":9.001426619},
{"learn":[2.848380047],"iteration":140,"passed_time":1.475591016,"remaining_time":8.989593496},
{"learn":[2.846680116],"iteration":141,"passed_time":1.486255568,"remaining_time":8.980332942},
{"learn":[2.845174085],"iteration":142,"passed_time":1.496564553,"remaining_time":8.968921833},
{"learn":[2.843514694],"iteration":143,"passed_time":1.506839023,"remaining_time":8.957320861},
{"learn":[2.840954443],"iteration":144,"passed_time":1.517096026,"remaining_time":8.94563519},
{"learn":[2.838303447],"iteration":145,"passed_time":1.527514392,"remaining_time":8.934912952},
{"learn":[2.835760348],"iteration":146,"passed_time":1.537614933,"remaining_time":8.922350599},
{"learn":[2.833282222],"iteration":147,"passed_time":1.547689795,"remaining_time":8.909673682},
{"learn":[2.83090054],"iteration":148,"passed_time":1.557828235,"remaining_time":8.897394816},
{"learn":[2.828529331],"iteration":149,"passed_time":1.568022114,"remaining_time":8.885458646},
{"learn":[2.826010972],"iteration":150,"passed_time":1.578144603,"remaining_time":8.873144156},
{"learn":[2.823672417],"iteration":151,"passed_time":1.588211633,"remaining_time":8.860549108},
{"learn":[2.822188627],"iteration":152,"passed_time":1.598468646,"remaining_time":8.849038845},
{"learn":[2.819952048],"iteration":153,"passed_time":1.609567557,"remaining_time":8.842169825},
{"learn":[2.817600912],"iteration":154,"passed_time":1.620215726,"remaining_time":8.832788959},
{"learn":[2.816478667],"iteration":155,"passed_time":1.630560113,"remaining_time":8.821748303},
{"learn":[2.814334407],"iteration":156,"passed_time":1.640679472,"remaining_time":8.809508249},
{"learn":[2.812196408],"iteration":157,"passed_time":1.651182596,"remaining_time":8.799340161},
{"learn":[2.810061089],"iteration":158,"passed_time":1.661275142,"remaining_time":8.786996189},
{"learn":[2.808854566],"iteration":159,"passed_time":1.671290879,"remaining_time":8.774277114},
{"learn":[2.806923555],"iteration":160,"passed_time":1.681465816,"remaining_time":8.76242124},
{"learn":[2.804797479],"iteration":161,"passed_time":1.691721301,"remaining_time":8.751002778},
{"learn":[2.802763128],"iteration":162,"passed_time":1.701818882,"remaining_time":8.738787754},
{"learn":[2.800784003],"iteration":163,"passed_time":1.711964762,"remaining_time":8.726844761},
{"learn":[2.798867023],"iteration":164,"passed_time":1.722717289,"remaining_time":8.717993553},
{"learn":[2.796970297],"iteration":165,"passed_time":1.733010553,"remaining_time":8.706812054},
{"learn":[2.795401748],"iteration":166,"passed_time":1.74318459,"remaining_time":8.695046489},
{"learn":[2.793473965],"iteration":167,"passed_time":1.753349559,"remaining_time":8.68325496},
{"learn":[2.791683205],"iteration":168,"passed_time":1.763826603,"remaining_time":8.673017202},
{"learn":[2.789839519],"iteration":169,"passed_time":1.774231176,"remaining_time":8.6624228},
{"learn":[2.788125501],"iteration":170,"passed_time":1.784527759,"remaining_time":8.651307089},
{"learn":[2.78633167],"iteration":171,"passed_time":1.794597962,"remaining_time":8.639111121},
{"learn":[2.784625425],"iteration":172,"passed_time":1.804905988,"remaining_time":8.628076601},
{"learn":[2.782990813],"iteration":173,"passed_time":1.815073102,"remaining_time":8.616381509},
{"learn":[2.781296211],"iteration":174,"passed_time":1.82537865,"remaining_time":8.605356494},
{"learn":[2.779718007],"iteration":175,"passed_time":1.835851628,"remaining_time":8.595123533},
{"learn":[2.778121967],"iteration":176,"passed_time":1.846721559,"remaining_time":8.586733575},
{"learn":[2.776518135],"iteration":177,"passed_time":1.856956827,"remaining_time":8.575384899},
{"learn":[2.775112706],"iteration":178,"passed_time":1.867276583,"remaining_time":8.564436173},
{"learn":[2.774029947],"iteration":179,"passed_time":1.87684306,"remaining_time":8.550062828},
{"learn":[2.772934298],"iteration":180,"passed_time":1.887316219,"remaining_time":8.539845211},
{"learn":[2.771461118],"iteration":181,"passed_time":1.89824405,"remaining_time":8.531668311},
{"learn":[2.770558027],"iteration":182,"passed_time":1.908005515,"remaining_time":8.518254131},
{"learn":[2.769028967],"iteration":183,"passed_time":1.91842386,"remaining_time":8.507792771},
{"learn":[2.767564777],"iteration":184,"passed_time":1.92908347,"remaining_time":8.498394747},
{"learn":[2.766026661],"iteration":185,"passed_time":1.939261447,"remaining_time":8.486875364},
{"learn":[2.76457779],"iteration":186,"passed_time":1.949606405,"remaining_time":8.476096294},
{"learn":[2.763564831],"iteration":187,"passed_time":1.9595642,"remaining_time":8.463649629},
{"learn":[2.762174141],"iteration":188,"passed_time":1.969824822,"remaining_time":8.452528733},
{"learn":[2.760760145],"iteration":189,"passed_time":1.980307958,"remaining_time":8.442365507},
{"learn":[2.759970981],"iteration":190,"passed_time":1.990450187,"remaining_time":8.430754979},
{"learn":[2.758912659],"iteration":191,"passed_time":2.000752021,"remaining_time":8.419831422},
{"learn":[2.757594861],"iteration":192,"passed_time":2.011148743,"remaining_time":8.409311067},
{"learn":[2.756227726],"iteration":193,"passed_time":2.021468091,"remaining_time":8.398470524},
{"learn":[2.754993295],"iteration":194,"passed_time":2.031660781,"remaining_time":8.387112455},
{"learn":[2.753694835],"iteration":195,"passed_time":2.041896857,"remaining_time":8.375944251},
{"learn":[2.75239346],"iteration":196,"passed_time":2.052106898,"remaining_time":8.364679384},
{"learn":[2.751218906],"iteration":197,"passed_time":2.06232,"remaining_time":8.353437576},
{"learn":[2.749938874],"iteration":198,"passed_time":2.072441572,"remaining_time":8.341837683},
{"learn":[2.748611331],"iteration":199,"passed_time":2.083136184,"remaining_time":8.332544737},
{"learn":[2.747000397],"iteration":200,"passed_time":2.093909348,"remaining_time":8.323550094},
{"learn":[2.745925864],"iteration":201,"passed_time":2.104666691,"remaining_time":8.314475343},
{"learn":[2.744775413],"iteration":202,"passed_time":2.115220997,"remaining_time":8.304586869},
{"learn":[2.743581994],"iteration":203,"passed_time":2.126020048,"remaining_time":8.295646855},
{"learn":[2.742407429],"iteration":204,"passed_time":2.136751203,"remaining_time":8.286425397},
{"learn":[2.741236048],"iteration":205,"passed_time":2.14737033,"remaining_time":8.276757486},
{"learn":[2.740187528],"iteration":206,"passed_time":2.157474168,"remaining_time":8.265106352},
{"learn":[2.739217063],"iteration":207,"passed_time":2.167486758,"remaining_time":8.253122657},
{"learn":[2.738329915],"iteration":208,"passed_time":2.177624141,"remaining_time":8.241630122},
{"learn":[2.73741743],"iteration":209,"passed_time":2.187771594,"remaining_time":8.230188378},
{"learn":[2.736266324],"iteration":210,"passed_time":2.197948471,"remaining_time":8.218868927},
{"learn":[2.735102136],"iteration":211,"passed_time":2.20842158,"remaining_time":8.208661345},
{"learn":[2.734010869],"iteration":212,"passed_time":2.218788644,"remaining_time":8.19805945},
{"learn":[2.73296561],"iteration":213,"passed_time":2.229327396,"remaining_time":8.188090344},
{"learn":[2.732236136],"iteration":214,"passed_time":2.239296832,"remaining_time":8.176037271},
{"learn":[2.731161531],"iteration":215,"passed_time":2.249491776,"remaining_time":8.164822003},
{"learn":[2.73048365],"iteration":216,"passed_time":2.259306667,"remaining_time":8.152244794},
{"learn":[2.729637722],"iteration":217,"passed_time":2.269572974,"remaining_time":8.141312229},
{"learn":[2.72858005],"iteration":218,"passed_time":2.279889653,"remaining_time":8.130565383},
{"learn":[2.727937088],"iteration":219,"passed_time":2.289631558,"remaining_time":8.117784614},
{"learn":[2.726904979],"iteration":220,"passed_time":2.299869125,"remaining_time":8.106778498},
{"learn":[2.725874417],"iteration":221,"passed_time":2.309875053,"remaining_time":8.094967529},
{"learn":[2.724852307],"iteration":222,"passed_time":2.322368227,"remaining_time":8.09183907},
{"learn":[2.723501909],"iteration":223,"passed_time":2.33348766,"remaining_time":8.083867967},
{"learn":[2.722529813],"iteration":224,"passed_time":2.34371175,"remaining_time":8.072784918},
{"learn":[2.721597765],"iteration":225,"passed_time":2.354056288,"remaining_time":8.062121979},
{"learn":[2.720759461],"iteration":226,"passed_time":2.363810827,"remaining_time":8.049452729},
{"learn":[2.719835133],"iteration":227,"passed_time":2.374203588,"remaining_time":8.038970044},
{"learn":[2.718872349],"iteration":228,"passed_time":2.384393993,"remaining_time":8.02780685},
{"learn":[2.71816111],"iteration":229,"passed_time":2.394338882,"remaining_time":8.015830171},
{"learn":[2.717121496],"iteration":230,"passed_time":2.404082816,"remaining_time":8.003202101},
{"learn":[2.716228937],"iteration":231,"passed_time":2.414270126,"remaining_time":7.992066623},
{"learn":[2.715332098],"iteration":232,"passed_time":2.424466553,"remaining_time":7.980969296},
{"learn":[2.714407256],"iteration":233,"passed_time":2.434433778,"remaining_time":7.969129377},
{"learn":[2.713433361],"iteration":234,"passed_time":2.444807905,"remaining_time":7.958629988},
{"learn":[2.712429221],"iteration":235,"passed_time":2.455791972,"remaining_time":7.950106214},
{"learn":[2.711275093],"iteration":236,"passed_time":2.466479195,"remaining_time":7.940606017},
{"learn":[2.710526372],"iteration":237,"passed_time":2.477516529,"remaining_time":7.932216785},
{"learn":[2.709882266],"iteration":238,"passed_time":2.487814339,"remaining_time":7.921450677},
{"learn":[2.709045428],"iteration":239,"passed_time":2.497719387,"remaining_time":7.909444726},
{"learn":[2.708201524],"iteration":240,"passed_time":2.507861952,"remaining_time":7.898204238},
{"learn":[2.707330343],"iteration":241,"passed_time":2.517707647,"remaining_time":7.88604296},
{"learn":[2.706498602],"iteration":242,"passed_time":2.527741372,"remaining_time":7.874486495},
{"learn":[2.705611917],"iteration":243,"passed_time":2.53813046,"remaining_time":7.864043556},
{"learn":[2.705117424],"iteration":244,"passed_time":2.548052179,"remaining_time":7.852160797},
{"learn":[2.704498671],"iteration":245,"passed_time":2.558420116,"remaining_time":7.841661656},
{"learn":[2.703466914],"iteration":246,"passed_time":2.569051184,"remaining_time":7.831965755},
{"learn":[2.702719406],"iteration":247,"passed_time":2.579270002,"remaining_time":7.821012263},
{"learn":[2.701891792],"iteration":248,"passed_time":2.589310996,"remaining_time":7.809528345},
{"learn":[2.701151181],"iteration":249,"passed_time":2.600271884,"remaining_time":7.800815651},
{"learn":[2.700402819],"iteration":250,"passed_time":2.610645919,"remaining_time":7.790333839},
{"learn":[2.699341455],"iteration":251,"passed_time":2.621571625,"remaining_time":7.781490378},
{"learn":[2.698424984],"iteration":252,"passed_time":2.632738125,"remaining_time":7.773341419},
{"learn":[2.697803009],"iteration":253,"passed_time":2.642392776,"remaining_time":7.760728388},
{"learn":[2.696957166],"iteration":254,"passed_time":2.652700175,"remaining_time":7.75004561},
{"learn":[2.695923294],"iteration":255,"passed_time":2.662881835,"remaining_time":7.739000332},
{"learn":[2.695537368],"iteration":256,"passed_time":2.672832639,"remaining_time":7.727294361},
{"learn":[2.694795503],"iteration":257,"passed_time":2.682908411,"remaining_time":7.7159614},
{"learn":[2.694040952],"iteration":258,"passed_time":2.693198168,"remaining_time":7.705250357},
{"learn":[2.693117529],"iteration":259,"passed_time":2.703234213,"remaining_time":7.693820451},
{"learn":[2.692421403],"iteration":260,"passed_time":2.713282027,"remaining_time":7.682434551},
{"learn":[2.691525951],"iteration":261,"passed_time":2.723629155,"remaining_time":7.671901972},
{"learn":[2.690649144],"iteration":262,"passed_time":2.73468974,"remaining_time":7.663370107},
{"learn":[2.689683102],"iteration":263,"passed_time":2.745423059,"remaining_time":7.65390671},
{"learn":[2.688803418],"iteration":264,"passed_time":2.755665881,"remaining_time":7.643073293},
{"learn":[2.687880129],"iteration":265,"passed_time":2.766500583,"remaining_time":7.633877548},
{"learn":[2.687194612],"iteration":266,"passed_time":2.776642129,"remaining_time":7.622766594},
{"learn":[2.686569418],"iteration":267,"passed_time":2.787079973,"remaining_time":7.612472165},
{"learn":[2.685834954],"iteration":268,"passed_time":2.796711782,"remaining_time":7.599986292},
{"learn":[2.685115904],"iteration":269,"passed_time":2.806789048,"remaining_time":7.588725944},
{"learn":[2.684543641],"iteration":270,"passed_time":2.817054409,"remaining_time":7.57798031},
{"learn":[2.683901155],"iteration":271,"passed_time":2.827283812,"remaining_time":7.567141967},
{"learn":[2.683311579],"iteration":272,"passed_time":2.837151597,"remaining_time":7.555345096},
{"learn":[2.682619892],"iteration":273,"passed_time":2.847475429,"remaining_time":7.544770663},
{"learn":[2.681728976],"iteration":274,"passed_time":2.857940521,"remaining_time":7.534570465},
{"learn":[2.681092668],"iteration":275,"passed_time":2.868669368,"remaining_time":7.525060226},
{"learn":[2.680574734],"iteration":276,"passed_time":2.878773963,"remaining_time":7.513911824},
{"learn":[2.679834579],"iteration":277,"passed_time":2.888291268,"remaining_time":7.501245667},
{"learn":[2.678672154],"iteration":278,"passed_time":2.899149022,"remaining_time":7.49206611},
{"learn":[2.677736705],"iteration":279,"passed_time":2.910092539,"remaining_time":7.483095101},
{"learn":[2.676884144],"iteration":280,"passed_time":2.920888001,"remaining_time":7.473731219},
{"learn":[2.676226896],"iteration":281,"passed_time":2.931423324,"remaining_time":7.463694847},
{"learn":[2.67550642],"iteration":282,"passed_time":2.941444889,"remaining_time":7.452353305},
{"learn":[2.675009599],"iteration":283,"passed_time":2.951258127,"remaining_time":7.440495841},
{"learn":[2.674327639],"iteration":284,"passed_time":2.961441751,"remaining_time":7.429581937},
{"learn":[2.673713527],"iteration":285,"passed_time":2.971930101,"remaining_time":7.419433888},
{"learn":[2.673097775],"iteration":286,"passed_time":2.981919249,"remaining_time":7.408043291},
{"learn":[2.672105683],"iteration":287,"passed_time":2.992451433,"remaining_time":7.398004933},
{"learn":[2.671554954],"iteration":288,"passed_time":3.00275669,"remaining_time":7.387404867},
{"learn":[2.670959397],"iteration":289,"passed_time":3.012497526,"remaining_time":7.375424976},
{"learn":[2.670329766],"iteration":290,"passed_time":3.022946628,"remaining_time":7.365186114},
{"learn":[2.669713105],"iteration":291,"passed_time":3.033263613,"remaining_time":7.354625473},
{"learn":[2.66910409],"iteration":292,"passed_time":3.043889399,"remaining_time":7.344811621},
{"learn":[2.668514783],"iteration":293,"passed_time":3.055972314,"remaining_time":7.338491339},
{"learn":[2.66770257],"iteration":294,"passed_time":3.067161055,"remaining_time":7.329995064},
{"learn":[2.667325999],"iteration":295,"passed_time":3.07748996,"remaining_time":7.31943558},
{"learn":[2.66677954],"iteration":296,"passed_time":3.087474271,"remaining_time":7.308061994},
{"learn":[2.666202282],"iteration":297,"passed_time":3.097974572,"remaining_time":7.297913253},
{"learn":[2.665625048],"iteration":298,"passed_time":3.108393053,"remaining_time":7.287570334},
{"learn":[2.665058073],"iteration":299,"passed_time":3.118679367,"remaining_time":7.276918522},
{"learn":[2.664461322],"iteration":300,"passed_time":3.129648858,"remaining_time":7.267855653},
{"learn":[2.663859397],"iteration":301,"passed_time":3.140130283,"remaining_time":7.257652112},
{"learn":[2.663274713],"iteration":302,"passed_time":3.149944506,"remaining_time":7.24591195},
{"learn":[2.662402188],"iteration":303,"passed_time":3.160698587,"remaining_time":7.236336239},
{"learn":[2.661520196],"iteration":304,"passed_time":3.170876856,"remaining_time":7.225440705},
{"learn":[2.661086683],"iteration":305,"passed_time":3.180851177,"remaining_time":7.214087311},
{"learn":[2.66051945],"iteration":306,"passed_time":3.191380572,"remaining_time":7.203995885},
{"learn":[2.660177525],"iteration":307,"passed_time":3.200843492,"remaining_time":7.191505508},
{"learn":[2.659521044],"iteration":308,"passed_time":3.210773283,"remaining_time":7.180078765},
{"learn":[2.659059479],"iteration":309,"passed_time":3.220930736,"remaining_time":7.169168412},
{"learn":[2.658450252],"iteration":310,"passed_time":3.23094868,"remaining_time":7.157953827},
{"learn":[2.657496455],"iteration":311,"passed_time":3.241894541,"remaining_time":7.148793091},
{"learn":[2.657173057],"iteration":312,"passed_time":3.25191142,"remaining_time":7.137581935},
{"learn":[2.656481791],"iteration":313,"passed_time":3.262800697,"remaining_time":7.128284326},
{"learn":[2.655862679],"iteration":314,"passed_time":3.272781929,"remaining_time":7.117001974},
{"learn":[2.655342024],"iteration":315,"passed_time":3.283035813,"remaining_time":7.106318025},
{"learn":[2.654599174],"iteration":316,"passed_time":3.293667346,"remaining_time":7.096450464},
{"learn":[2.653916138],"iteration":317,"passed_time":3.304004672,"remaining_time":7.085947127},
{"learn":[2.653255276],"iteration":318,"passed_time":3.314626193,"remaining_time":7.076051527},
{"learn":[2.652426347],"iteration":319,"passed_time":3.325188901,"remaining_time":7.066026414},
{"learn":[2.651894246],"iteration":320,"passed_time":3.335526185,"remaining_time":7.055521119},
{"learn":[2.651256451],"iteration":321,"passed_time":3.345863846,"remaining_time":7.045017664},
{"learn":[2.650532317],"iteration":322,"passed_time":3.356319777,"remaining_time":7.034763125},
{"learn":[2.649658734],"iteration":323,"passed_time":3.366622226,"remaining_time":7.024187114},
{"learn":[2.649285082],"iteration":324,"passed_time":3.376792749,"remaining_time":7.013338786},
{"learn":[2.648562313],"iteration":325,"passed_time":3.387108737,"remaining_time":7.002795365},
{"learn":[2.647970379],"iteration":326,"passed_time":3.397336859,"remaining_time":6.992072497},
{"learn":[2.647449124],"iteration":327,"passed_time":3.407333544,"remaining_time":6.98087848},
{"learn":[2.646704807],"iteration":328,"passed_time":3.417435254,"remaining_time":6.969905944},
{"learn":[2.64618002],"iteration":329,"passed_time":3.427679025,"remaining_time":6.959227111},
{"learn":[2.645540138],"iteration":330,"passed_time":3.438038083,"remaining_time":6.948783921},
{"learn":[2.64511981],"iteration":331,"passed_time":3.44754822,"remaining_time":6.936633166},
{"learn":[2.6447962],"iteration":332,"passed_time":3.45732455,"remaining_time":6.925031456},
{"learn":[2.644095301],"iteration":333,"passed_time":3.468164992,"remaining_time":6.915562529},
{"learn":[2.643507602],"iteration":334,"passed_time":3.47857772,"remaining_time":6.905236369},
{"learn":[2.643008767],"iteration":335,"passed_time":3.488910112,"remaining_time":6.894750936},
{"learn":[2.641958589],"iteration":336,"passed_time":3.500343823,"remaining_time":6.8864331},
{"learn":[2.641160057],"iteration":337,"passed_time":3.511437759,"remaining_time":6.877431351},
{"learn":[2.640559203],"iteration":338,"passed_time":3.522312085,"remaining_time":6.867989051},
{"learn":[2.639946784],"iteration":339,"passed_time":3.532648127,"remaining_time":6.857493424},
{"learn":[2.63916375],"iteration":340,"passed_time":3.543124421,"remaining_time":6.847269776},
{"learn":[2.638271562],"iteration":341,"passed_time":3.554006231,"remaining_time":6.837824854},
{"learn":[2.637541891],"iteration":342,"passed_time":3.564797538,"remaining_time":6.8281982},
{"learn":[2.637020551],"iteration":343,"passed_time":3.574927136,"remaining_time":6.817302911},
{"learn":[2.636334641],"iteration":344,"passed_time":3.585375845,"remaining_time":6.807017909},
{"learn":[2.635648958],"iteration":345,"passed_time":3.597047124,"remaining_time":6.799042829},
{"learn":[2.635074583],"iteration":346,"passed_time":3.607430165,"remaining_time":6.788622184},
{"learn":[2.634264712],"iteration":347,"passed_time":3.617674964,"remaining_time":6.777942749},
{"learn":[2.633593048],"iteration":348,"passed_time":3.628816651,"remaining_time":6.768938795},
{"learn":[2.63310283],"iteration":349,"passed_time":3.639402446,"remaining_time":6.758890257},
{"learn":[2.632583716],"iteration":350,"passed_time":3.649157674,"remaining_time":6.747302935},
{"learn":[2.632122542],"iteration":351,"passed_time":3.659177114,"remaining_time":6.736212414},
{"learn":[2.631295341],"iteration":352,"passed_time":3.669964608,"remaining_time":6.726535698},
{"learn":[2.630842629],"iteration":353,"passed_time":3.680243322,"remaining_time":6.715924255},
{"learn":[2.630038144],"iteration":354,"passed_time":3.691302973,"remaining_time":6.706733571},
{"learn":[2.629548166],"iteration":355,"passed_time":3.701395233,"remaining_time":6.695782388},
{"learn":[2.628874638],"iteration":356,"passed_time":3.711645055,"remaining_time":6.685119804},
{"learn":[2.628168119],"iteration":357,"passed_time":3.721815339,"remaining_time":6.674316892},
{"learn":[2.627725236],"iteration":358,"passed_time":3.731657604,"remaining_time":6.662931823},
{"learn":[2.627109994],"iteration":359,"passed_time":3.742021044,"remaining_time":6.652481856},
{"learn":[2.626506027],"iteration":360,"passed_time":3.752499495,"remaining_time":6.642235949},
{"learn":[2.626091007],"iteration":361,"passed_time":3.762562314,"remaining_time":6.631256234},
{"learn":[2.625533137],"iteration":362,"passed_time":3.772556421,"remaining_time":6.620160992},
{"learn":[2.62469016],"iteration":363,"passed_time":3.783184015,"remaining_time":6.610178663},
{"learn":[2.623936974],"iteration":364,"passed_time":3.793978922,"remaining_time":6.600483878},
{"learn":[2.623498059],"iteration":365,"passed_time":3.804337548,"remaining_time":6.590027338},
{"learn":[2.623037501],"iteration":366,"passed_time":3.814184699,"remaining_time":6.578689141},
{"learn":[2.622508669],"iteration":367,"passed_time":3.824677911,"remaining_time":6.568468587},
{"learn":[2.621878126],"iteration":368,"passed_time":3.834435167,"remaining_time":6.55698805},
{"learn":[2.621480091],"iteration":369,"passed_time":3.844329763,"remaining_time":6.545750678},
{"learn":[2.620873475],"iteration":370,"passed_time":3.855152881,"remaining_time":6.536094777},
{"learn":[2.620488122],"iteration":371,"passed_time":3.864940859,"remaining_time":6.524685106},
{"learn":[2.619913524],"iteration":372,"passed_time":3.875731283,"remaining_time":6.514969208},
{"learn":[2.619316308],"iteration":373,"passed_time":3.886362449,"remaining_time":6.504980998},
{"learn":[2.618774773],"iteration":374,"passed_time":3.896521606,"remaining_time":6.494202676},
{"learn":[2.618366262],"iteration":375,"passed_time":3.907306993,"remaining_time":6.484466925},
{"learn":[2.617940913],"iteration":376,"passed_time":3.917432012,"remaining_time":6.473634332},
{"learn":[2.61728165],"iteration":377,"passed_time":3.928428987,"remaining_time":6.46424029},
{"learn":[2.616765528],"iteration":378,"passed_time":3.938783674,"remaining_time":6.453785386},
{"learn":[2.616406933],"iteration":379,"passed_time":3.948253365,"remaining_time":6.44188707},
{"learn":[2.615742994],"iteration":380,"passed_time":3.958487454,"remaining_time":6.431243397},
{"learn":[2.615279384],"iteration":381,"passed_time":3.969309251,"remaining_time":6.421552662},
{"learn":[2.614859005],"iteration":382,"passed_time":3.978875554,"remaining_time":6.409833464},
{"learn":[2.614338787],"iteration":383,"passed_time":3.988814303,"remaining_time":6.398722945},
{"learn":[2.613772007],"iteration":384,"passed_time":3.999621934,"remaining_time":6.389006465},
{"learn":[2.612968081],"iteration":385,"passed_time":4.010943614,"remaining_time":6.380102018},
{"learn":[2.612264818],"iteration":386,"passed_time":4.021121735,"remaining_time":6.369373704},
{"learn":[2.611729782],"iteration":387,"passed_time":4.030863494,"remaining_time":6.357959945},
{"learn":[2.611261637],"iteration":388,"passed_time":4.040600917,"remaining_time":6.346547969},
{"learn":[2.610687959],"iteration":389,"passed_time":4.050622419,"remaining_time":6.335588911},
{"learn":[2.610316152],"iteration":390,"passed_time":4.060675334,"remaining_time":6.324683577},
{"learn":[2.609890242],"iteration":391,"passed_time":4.070405141,"remaining_time":6.313281443},
{"learn":[2.609313065],"iteration":392,"passed_time":4.081096172,"remaining_time":6.303372459},
{"learn":[2.608902351],"iteration":393,"passed_time":4.092173028,"remaining_time":6.294052931},
{"learn":[2.608444633],"iteration":394,"passed_time":4.102245555,"remaining_time":6.28318623},
{"learn":[2.607920566],"iteration":395,"passed_time":4.113215948,"remaining_time":6.273693012},
{"learn":[2.607245397],"iteration":396,"passed_time":4.123652864,"remaining_time":6.263382058},
{"learn":[2.606671286],"iteration":397,"passed_time":4.134866241,"remaining_time":6.254244917},
{"learn":[2.606255583],"iteration":398,"passed_time":4.144710455,"remaining_time":6.243035046},
{"learn":[2.605942635],"iteration":399,"passed_time":4.154889225,"remaining_time":6.232333837},
{"learn":[2.605366373],"iteration":400,"passed_time":4.165240831,"remaining_time":6.221893411},
{"learn":[2.604529478],"iteration":401,"passed_time":4.176828379,"remaining_time":6.213291967},
{"learn":[2.604116738],"iteration":402,"passed_time":4.186721203,"remaining_time":6.202165157},
{"learn":[2.603448575],"iteration":403,"passed_time":4.197826213,"remaining_time":6.19283273},
{"learn":[2.602881536],"iteration":404,"passed_time":4.207906804,"remaining_time":6.181986539},
{"learn":[2.602403136],"iteration":405,"passed_time":4.218545264,"remaining_time":6.171960312},
{"learn":[2.601951094],"iteration":406,"passed_time":4.228349042,"remaining_time":6.160714943},
{"learn":[2.601268418],"iteration":407,"passed_time":4.239602504,"remaining_time":6.151580104},
{"learn":[2.600779987],"iteration":408,"passed_time":4.249917121,"remaining_time":6.141078285},
{"learn":[2.600217705],"iteration":409,"passed_time":4.260640895,"remaining_time":6.131166165},
{"learn":[2.599520928],"iteration":410,"passed_time":4.270908969,"remaining_time":6.120597038},
{"learn":[2.599073793],"iteration":411,"passed_time":4.281205047,"remaining_time":6.110069338},
{"learn":[2.598557294],"iteration":412,"passed_time":4.291178142,"remaining_time":6.099083704},
{"learn":[2.598173495],"iteration":413,"passed_time":4.30115348,"remaining_time":6.088106133},
{"learn":[2.597460785],"iteration":414,"passed_time":4.311586686,"remaining_time":6.077778823},
{"learn":[2.596917826],"iteration":415,"passed_time":4.321666485,"remaining_time":6.066954873},
{"learn":[2.596313314],"iteration":416,"passed_time":4.332546841,"remaining_time":6.057253737},
{"learn":[2.595759531],"iteration":417,"passed_time":4.343554334,"remaining_time":6.047723977},
{"learn":[2.595205126],"iteration":418,"passed_time":4.354099851,"remaining_time":6.037546571},
{"learn":[2.594686181],"iteration":419,"passed_time":4.364073846,"remaining_time":6.026578169},
{"learn":[2.594075238],"iteration":420,"passed_time":4.374901195,"remaining_time":6.016788104},
{"learn":[2.593458625],"iteration":421,"passed_time":4.385442944,"remaining_time":6.006601947},
{"learn":[2.592904508],"iteration":422,"passed_time":4.39585578,"remaining_time":5.996238262},
{"learn":[2.592356676],"iteration":423,"passed_time":4.4061937,"remaining_time":5.985772574},
{"learn":[2.591954825],"iteration":424,"passed_time":4.416014584,"remaining_time":5.974607966},
{"learn":[2.591285125],"iteration":425,"passed_time":4.427042861,"remaining_time":5.965076531},
{"learn":[2.590759873],"iteration":426,"passed_time":4.437354049,"remaining_time":5.954575808},
{"learn":[2.590303997],"iteration":427,"passed_time":4.447399831,"remaining_time":5.94372127},
{"learn":[2.589541637],"iteration":428,"passed_time":4.458846185,"remaining_time":5.934734666},
{"learn":[2.588976345],"iteration":429,"passed_time":4.46982174,"remaining_time":5.925112539},
{"learn":[2.588556748],"iteration":430,"passed_time":4.479794331,"remaining_time":5.914160033},
{"learn":[2.58801402],"iteration":431,"passed_time":4.490763467,"remaining_time":5.904522337},
{"learn":[2.587514504],"iteration":432,"passed_time":4.501505783,"remaining_time":5.894581476},
{"learn":[2.587007369],"iteration":433,"passed_time":4.51212268,"remaining_time":5.884473356},
{"learn":[2.58656126],"iteration":434,"passed_time":4.522052871,"remaining_time":5.87347097},
{"learn":[2.5859586],"iteration":435,"passed_time":4.532269202,"remaining_time":5.862843646},
{"learn":[2.585546237],"iteration":436,"passed_time":4.542298625,"remaining_time":5.851977404},
{"learn":[2.584870765],"iteration":437,"passed_time":4.553597946,"remaining_time":5.842744397},
{"learn":[2.584464563],"iteration":438,"passed_time":4.5637518,"remaining_time":5.832038178},
{"learn":[2.583873499],"iteration":439,"passed_time":4.57487563,"remaining_time":5.822568984},
{"learn":[2.583444269],"iteration":440,"passed_time":4.585762522,"remaining_time":5.81279195},
{"learn":[2.582922072],"iteration":441,"passed_time":4.596749029,"remaining_time":5.803135652},
{"learn":[2.58237231],"iteration":442,"passed_time":4.606919163,"remaining_time":5.792446894},
{"learn":[2.581824162],"iteration":443,"passed_time":4.617284982,"remaining_time":5.782005518},
{"learn":[2.581210623],"iteration":444,"passed_time":4.627839103,"remaining_time":5.771799331},
{"learn":[2.580800888],"iteration":445,"passed_time":4.637883008,"remaining_time":5.760957817},
{"learn":[2.580215939],"iteration":446,"passed_time":4.648838071,"remaining_time":5.751247099},
{"learn":[2.579773245],"iteration":447,"passed_time":4.659332216,"remaining_time":5.740962909},
{"learn":[2.579082916],"iteration":448,"passed_time":4.670589578,"remaining_time":5.731614382},
{"learn":[2.578477259],"iteration":449,"passed_time":4.681690052,"remaining_time":5.722065619},
{"learn":[2.577999513],"iteration":450,"passed_time":4.691718773,"remaining_time":5.711205335},
{"learn":[2.577405872],"iteration":451,"passed_time":4.702823745,"remaining_time":5.701653567},
{"learn":[2.57687493],"iteration":452,"passed_time":4.713093603,"remaining_time":5.691086536},
{"learn":[2.57621017],"iteration":453,"passed_time":4.724519023,"remaining_time":5.681910543},
{"learn":[2.575814981],"iteration":454,"passed_time":4.734797114,"remaining_time":5.671350389},
{"learn":[2.575263909],"iteration":455,"passed_time":4.745403773,"remaining_time":5.661183449},
{"learn":[2.574762393],"iteration":456,"passed_time":4.755360911,"remaining_time":5.650242833},
{"learn":[2.574241869],"iteration":457,"passed_time":4.766125567,"remaining_time":5.640262134},
{"learn":[2.573830614],"iteration":458,"passed_time":4.776408091,"remaining_time":5.629709754},
{"learn":[2.573293424],"iteration":459,"passed_time":4.787337935,"remaining_time":5.619918446},
{"learn":[2.572796048],"iteration":460,"passed_time":4.797000717,"remaining_time":5.608640752},
{"learn":[2.572187736],"iteration":461,"passed_time":4.808450749,"remaining_time":5.599451305},
{"learn":[2.571635807],"iteration":462,"passed_time":4.818634548,"remaining_time":5.588783482},
{"learn":[2.571253155],"iteration":463,"passed_time":4.829258579,"remaining_time":5.57862629},
{"learn":[2.570635582],"iteration":464,"passed_time":4.839366927,"remaining_time":5.567873777},
{"learn":[2.570173485],"iteration":465,"passed_time":4.848964348,"remaining_time":5.556538545},
{"learn":[2.569637436],"iteration":466,"passed_time":4.859537631,"remaining_time":5.546324534},
{"learn":[2.569281013],"iteration":467,"passed_time":4.869637276,"remaining_time":5.535570579},
{"learn":[2.568824438],"iteration":468,"passed_time":4.879808102,"remaining_time":5.524900004},
{"learn":[2.568346108],"iteration":469,"passed_time":4.890204561,"remaining_time":5.514485994},
{"learn":[2.567824858],"iteration":470,"passed_time":4.900364248,"remaining_time":5.50380613},
{"learn":[2.567362436],"iteration":471,"passed_time":4.910676304,"remaining_time":5.493298917},
{"learn":[2.566763948],"iteration":472,"passed_time":4.921772806,"remaining_time":5.48366653},
{"learn":[2.566144462],"iteration":473,"passed_time":4.932443242,"remaining_time":5.473555159},
{"learn":[2.56558681],"iteration":474,"passed_time":4.943233329,"remaining_time":5.46357368},
{"learn":[2.565272199],"iteration":475,"passed_time":4.95285487,"remaining_time":5.452302419},
{"learn":[2.564686725],"iteration":476,"passed_time":4.963052086,"remaining_time":5.441669268},
{"learn":[2.564185166],"iteration":477,"passed_time":4.973192397,"remaining_time":5.430975797},
{"learn":[2.563668163],"iteration":478,"passed_time":4.984092101,"remaining_time":5.421110615},
{"learn":[2.563415324],"iteration":479,"passed_time":4.994170244,"remaining_time":5.410351097},
{"learn":[2.562989551],"iteration":480,"passed_time":5.003971651,"remaining_time":5.399295815},
{"learn":[2.562653229],"iteration":481,"passed_time":5.013289524,"remaining_time":5.387726086},
{"learn":[2.562131968],"iteration":482,"passed_time":5.023372402,"remaining_time":5.376984538},
{"learn":[2.561548766],"iteration":483,"passed_time":5.033505078,"remaining_time":5.366298802},
{"learn":[2.561146819],"iteration":484,"passed_time":5.043607883,"remaining_time":5.355583629},
{"learn":[2.560697023],"iteration":485,"passed_time":5.053952272,"remaining_time":5.345126477},
{"learn":[2.560193799],"iteration":486,"passed_time":5.068027522,"remaining_time":5.338599833},
{"learn":[2.55960638],"iteration":487,"passed_time":5.083627816,"remaining_time":5.333642298},
{"learn":[2.559111116],"iteration":488,"passed_time":5.096627971,"remaining_time":5.325924117},
{"learn":[2.558652566],"iteration":489,"passed_time":5.112375762,"remaining_time":5.321044161},
{"learn":[2.558431966],"iteration":490,"passed_time":5.124863259,"remaining_time":5.31274012},
{"learn":[2.558174653],"iteration":491,"passed_time":5.139178936,"remaining_time":5.306306706},
{"learn":[2.557626856],"iteration":492,"passed_time":5.153496136,"remaining_time":5.299842882},
{"learn":[2.557278963],"iteration":493,"passed_time":5.165443455,"remaining_time":5.290919814},
{"learn":[2.556564432],"iteration":494,"passed_time":5.178170639,"remaining_time":5.282780146},
{"learn":[2.556227455],"iteration":495,"passed_time":5.190074357,"remaining_time":5.273785234},
{"learn":[2.555720921],"iteration":496,"passed_time":5.203116122,"remaining_time":5.265930401},
{"learn":[2.55512481],"iteration":497,"passed_time":5.216443854,"remaining_time":5.258343001},
{"learn":[2.554665722],"iteration":498,"passed_time":5.227461601,"remaining_time":5.248413351},
{"learn":[2.554299956],"iteration":499,"passed_time":5.238028737,"remaining_time":5.238028737},
{"learn":[2.553738711],"iteration":500,"passed_time":5.249035786,"remaining_time":5.228081552},
{"learn":[2.5531537],"iteration":501,"passed_time":5.259148577,"remaining_time":5.21724301},
{"learn":[2.552613259],"iteration":502,"passed_time":5.269886368,"remaining_time":5.207024901},
{"learn":[2.551948292],"iteration":503,"passed_time":5.280303482,"remaining_time":5.196489141},
{"learn":[2.551397258],"iteration":504,"passed_time":5.291350065,"remaining_time":5.186570856},
{"learn":[2.550885119],"iteration":505,"passed_time":5.301696286,"remaining_time":5.175964358},
{"learn":[2.550437724],"iteration":506,"passed_time":5.311516711,"remaining_time":5.164847611},
{"learn":[2.549944863],"iteration":507,"passed_time":5.322214497,"remaining_time":5.154585693},
{"learn":[2.549491563],"iteration":508,"passed_time":5.332668,"remaining_time":5.14408642},
{"learn":[2.548900626],"iteration":509,"passed_time":5.343819846,"remaining_time":5.134258283},
{"learn":[2.548520065],"iteration":510,"passed_time":5.353962836,"remaining_time":5.123459544},
{"learn":[2.547899716],"iteration":511,"passed_time":5.36506026,"remaining_time":5.11357306},
{"learn":[2.547322075],"iteration":512,"passed_time":5.376160638,"remaining_time":5.10368466},
{"learn":[2.546821151],"iteration":513,"passed_time":5.386508278,"remaining_time":5.093079812},
{"learn":[2.546288521],"iteration":514,"passed_time":5.396893908,"remaining_time":5.082511739},
{"learn":[2.545918613],"iteration":515,"passed_time":5.407063135,"remaining_time":5.07174139},
{"learn":[2.545467339],"iteration":516,"passed_time":5.417255766,"remaining_time":5.060995232},
{"learn":[2.544826092],"iteration":517,"passed_time":5.427481551,"remaining_time":5.050282061},
{"learn":[2.544275413],"iteration":518,"passed_time":5.438589819,"remaining_time":5.040388638},
{"learn":[2.543938729],"iteration":519,"passed_time":5.448452372,"remaining_time":5.029340651},
{"learn":[2.543503217],"iteration":520,"passed_time":5.45861496,"remaining_time":5.018573063},
{"learn":[2.543112671],"iteration":521,"passed_time":5.46900355,"remaining_time":5.008014745},
{"learn":[2.542829547],"iteration":522,"passed_time":5.479306142,"remaining_time":4.997378642},
{"learn":[2.542398582],"iteration":523,"passed_time":5.494077626,"remaining_time":4.99080334},
{"learn":[2.541833667],"iteration":524,"passed_time":5.505099659,"remaining_time":4.980804454},
{"learn":[2.541275973],"iteration":525,"passed_time":5.515999404,"remaining_time":4.970691478},
{"learn":[2.540748216],"iteration":526,"passed_time":5.526245147,"remaining_time":4.959988529},
{"learn":[2.540299399],"iteration":527,"passed_time":5.538347205,"remaining_time":4.950946744},
{"learn":[2.539913074],"iteration":528,"passed_time":5.548684917,"remaining_time":4.940322488},
{"learn":[2.539314086],"iteration":529,"passed_time":5.559569249,"remaining_time":4.930184051},
{"learn":[2.538721582],"iteration":530,"passed_time":5.570208919,"remaining_time":4.91982671},
{"learn":[2.538209614],"iteration":531,"passed_time":5.580874109,"remaining_time":4.909490757},
{"learn":[2.537760575],"iteration":532,"passed_time":5.591818212,"remaining_time":4.899397945},
{"learn":[2.537381304],"iteration":533,"passed_time":5.601941689,"remaining_time":4.888585818},
{"learn":[2.536928072],"iteration":534,"passed_time":5.61215184,"remaining_time":4.8778516},
{"learn":[2.536399993],"iteration":535,"passed_time":5.622157524,"remaining_time":4.866942334},
{"learn":[2.536142004],"iteration":536,"passed_time":5.631928712,"remaining_time":4.855834253},
{"learn":[2.535499935],"iteration":537,"passed_time":5.643051025,"remaining_time":4.845891401},
{"learn":[2.535099661],"iteration":538,"passed_time":5.652779333,"remaining_time":4.834751897},
{"learn":[2.534658761],"iteration":539,"passed_time":5.662507174,"remaining_time":4.823617222},
{"learn":[2.534246763],"iteration":540,"passed_time":5.672646333,"remaining_time":4.812836722},
{"learn":[2.53379156],"iteration":541,"passed_time":5.682729284,"remaining_time":4.802011092},
{"learn":[2.533395966],"iteration":542,"passed_time":5.693654997,"remaining_time":4.791897483},
{"learn":[2.532925804],"iteration":543,"passed_time":5.704584588,"remaining_time":4.78178414},
{"learn":[2.532448873],"iteration":544,"passed_time":5.71538699,"remaining_time":4.771561615},
{"learn":[2.531813279],"iteration":545,"passed_time":5.726048638,"remaining_time":4.76121993},
{"learn":[2.531435387],"iteration":546,"passed_time":5.735949015,"remaining_time":4.750246625},
{"learn":[2.530894475],"iteration":547,"passed_time":5.746275005,"remaining_time":4.739628289},
{"learn":[2.530258872],"iteration":548,"passed_time":5.757462449,"remaining_time":4.729718697},
{"learn":[2.529714216],"iteration":549,"passed_time":5.76778833,"remaining_time":4.719099542},
{"learn":[2.529212819],"iteration":550,"passed_time":5.778484029,"remaining_time":4.708782811},
{"learn":[2.528671283],"iteration":551,"passed_time":5.789801619,"remaining_time":4.69896943},
{"learn":[2.528101229],"iteration":552,"passed_time":5.800287018,"remaining_time":4.688477933},
{"learn":[2.527666813],"iteration":553,"passed_time":5.810427964,"remaining_time":4.677709155},
{"learn":[2.527083992],"iteration":554,"passed_time":5.821197153,"remaining_time":4.667446366},
{"learn":[2.526581268],"iteration":555,"passed_time":5.831486923,"remaining_time":4.65679891},
{"learn":[2.526127963],"iteration":556,"passed_time":5.841131981,"remaining_time":4.645639978},
{"learn":[2.52594212],"iteration":557,"passed_time":5.85069377,"remaining_time":4.634420513},
{"learn":[2.525454459],"iteration":558,"passed_time":5.861574103,"remaining_time":4.624247191},
{"learn":[2.524851736],"iteration":559,"passed_time":5.872343252,"remaining_time":4.613983984},
{"learn":[2.524303947],"iteration":560,"passed_time":5.883320713,"remaining_time":4.603881984},
{"learn":[2.523720386],"iteration":561,"passed_time":5.893695858,"remaining_time":4.593307448},
{"learn":[2.52343435],"iteration":562,"passed_time":5.90453348,"remaining_time":4.583092595},
{"learn":[2.522972179],"iteration":563,"passed_time":5.914782717,"remaining_time":4.572420682},
{"learn":[2.522450961],"iteration":564,"passed_time":5.925334532,"remaining_time":4.561983224},
{"learn":[2.522003324],"iteration":565,"passed_time":5.935095733,"remaining_time":4.550939131},
{"learn":[2.521700099],"iteration":566,"passed_time":5.944849772,"remaining_time":4.539894094},
{"learn":[2.521316157],"iteration":567,"passed_time":5.95549859,"remaining_time":4.529534139},
{"learn":[2.520798486],"iteration":568,"passed_time":5.968421542,"remaining_time":4.520895755},
{"learn":[2.520387829],"iteration":569,"passed_time":5.979272009,"remaining_time":4.510678884},
{"learn":[2.520125001],"iteration":570,"passed_time":5.989348608,"remaining_time":4.499878377},
{"learn":[2.51953117],"iteration":571,"passed_time":5.999755746,"remaining_time":4.489327726},
{"learn":[2.519085317],"iteration":572,"passed_time":6.009897178,"remaining_time":4.478579572},
{"learn":[2.518662614],"iteration":573,"passed_time":6.020435855,"remaining_time":4.468128352},
{"learn":[2.518243397],"iteration":574,"passed_time":6.03129165,"remaining_time":4.457911219},
{"learn":[2.517773828],"iteration":575,"passed_time":6.041511852,"remaining_time":4.447224002},
{"learn":[2.51732851],"iteration":576,"passed_time":6.051998026,"remaining_time":4.436733388},
{"learn":[2.516968533],"iteration":577,"passed_time":6.062268759,"remaining_time":4.426085496},
{"learn":[2.516342471],"iteration":578,"passed_time":6.0731724,"remaining_time":4.415899102},
{"learn":[2.515741663],"iteration":579,"passed_time":6.084020542,"remaining_time":4.405670048},
{"learn":[2.515331142],"iteration":580,"passed_time":6.094481023,"remaining_time":4.395159292},
{"learn":[2.514951045],"iteration":581,"passed_time":6.10468906,"remaining_time":4.3844674},
{"learn":[2.514557663],"iteration":582,"passed_time":6.11478992,"remaining_time":4.373700509},
{"learn":[2.514074928],"iteration":583,"passed_time":6.125556028,"remaining_time":4.363409774},
{"learn":[2.513473945],"iteration":584,"passed_time":6.137040977,"remaining_time":4.35362736},
{"learn":[2.512898943],"iteration":585,"passed_time":6.147175751,"remaining_time":4.342885258},
{"learn":[2.512264323],"iteration":586,"passed_time":6.157925116,"remaining_time":4.332577637},
{"learn":[2.511890637],"iteration":587,"passed_time":6.167960954,"remaining_time":4.321768559},
{"learn":[2.511376621],"iteration":588,"passed_time":6.178699798,"remaining_time":4.31145266},
{"learn":[2.510932019],"iteration":589,"passed_time":6.189105965,"remaining_time":4.300904145},
{"learn":[2.510393669],"iteration":590,"passed_time":6.199444795,"remaining_time":4.290309511},
{"learn":[2.509974326],"iteration":591,"passed_time":6.2096757,"remaining_time":4.279641361},
{"learn":[2.50953223],"iteration":592,"passed_time":6.219327958,"remaining_time":4.268577536},
{"learn":[2.509089685],"iteration":593,"passed_time":6.229501145,"remaining_time":4.25787452},
{"learn":[2.508583025],"iteration":594,"passed_time":6.240260977,"remaining_time":4.247572598},
{"learn":[2.508070596],"iteration":595,"passed_time":6.250895403,"remaining_time":4.237184132},
{"learn":[2.507695188],"iteration":596,"passed_time":6.261398621,"remaining_time":4.226706272},
{"learn":[2.507382888],"iteration":597,"passed_time":6.271820086,"remaining_time":4.216173369},
{"learn":[2.506930711],"iteration":598,"passed_time":6.282769951,"remaining_time":4.205994575},
{"learn":[2.506548139],"iteration":599,"passed_time":6.293390839,"remaining_time":4.195593892},
{"learn":[2.505928794],"iteration":600,"passed_time":6.303947539,"remaining_time":4.185149864},
{"learn":[2.505533956],"iteration":601,"passed_time":6.314001978,"remaining_time":4.1743734},
{"learn":[2.505087693],"iteration":602,"passed_time":6.324401867,"remaining_time":4.163826768},
{"learn":[2.50455992],"iteration":603,"passed_time":6.334510788,"remaining_time":4.153089854},
{"learn":[2.504069849],"iteration":604,"passed_time":6.345443722,"remaining_time":4.142893008},
{"learn":[2.503574953],"iteration":605,"passed_time":6.35652968,"remaining_time":4.132793224},
{"learn":[2.503285244],"iteration":606,"passed_time":6.366380979,"remaining_time":4.121890815},
{"learn":[2.502719456],"iteration":607,"passed_time":6.377628055,"remaining_time":4.111891772},
{"learn":[2.502133252],"iteration":608,"passed_time":6.388423986,"remaining_time":4.10159898},
{"learn":[2.501755348],"iteration":609,"passed_time":6.398960741,"remaining_time":4.091138835},
{"learn":[2.501125452],"iteration":610,"passed_time":6.4103175,"remaining_time":4.081200503},
{"learn":[2.500594507],"iteration":611,"passed_time":6.420614644,"remaining_time":4.070585755},
{"learn":[2.500119478],"iteration":612,"passed_time":6.430767497,"remaining_time":4.059880948},
{"learn":[2.499768649],"iteration":613,"passed_time":6.44111362,"remaining_time":4.049299442},
{"learn":[2.499259428],"iteration":614,"passed_time":6.451662916,"remaining_time":4.03884589},
{"learn":[2.498751977],"iteration":615,"passed_time":6.461298427,"remaining_time":4.027822396},
{"learn":[2.498314834],"iteration":616,"passed_time":6.471779727,"remaining_time":4.017328421},
{"learn":[2.497989191],"iteration":617,"passed_time":6.482440895,"remaining_time":4.006945667},
{"learn":[2.497659322],"iteration":618,"passed_time":6.491951911,"remaining_time":3.995854084},
{"learn":[2.497144546],"iteration":619,"passed_time":6.502208613,"remaining_time":3.985224634},
{"learn":[2.496760272],"iteration":620,"passed_time":6.512961553,"remaining_time":3.974899241},
{"learn":[2.496379935],"iteration":621,"passed_time":6.525551535,"remaining_time":3.965688875},
{"learn":[2.496058227],"iteration":622,"passed_time":6.536918359,"remaining_time":3.955727482},
{"learn":[2.495734267],"iteration":623,"passed_time":6.548758997,"remaining_time":3.946047088},
{"learn":[2.495220248],"iteration":624,"passed_time":6.560897907,"remaining_time":3.936538744},
{"learn":[2.494928429],"iteration":625,"passed_time":6.571362143,"remaining_time":3.926021472},
{"learn":[2.494605261],"iteration":626,"passed_time":6.581657664,"remaining_time":3.915404001},
{"learn":[2.494177777],"iteration":627,"passed_time":6.591706822,"remaining_time":3.90464162},
{"learn":[2.49370507],"iteration":628,"passed_time":6.60152173,"remaining_time":3.893743342},
{"learn":[2.493266924],"iteration":629,"passed_time":6.612058974,"remaining_time":3.883272731},
{"learn":[2.492788029],"iteration":630,"passed_time":6.622318934,"remaining_time":3.872639757},
{"learn":[2.492402738],"iteration":631,"passed_time":6.632722127,"remaining_time":3.862091365},
{"learn":[2.49202734],"iteration":632,"passed_time":6.643507209,"remaining_time":3.851764843},
{"learn":[2.49156289],"iteration":633,"passed_time":6.65390476,"remaining_time":3.841213158},
{"learn":[2.491002004],"iteration":634,"passed_time":6.664268317,"remaining_time":3.830642418},
{"learn":[2.490476411],"iteration":635,"passed_time":6.674624992,"remaining_time":3.820068392},
{"learn":[2.490012763],"iteration":636,"passed_time":6.686077901,"remaining_time":3.810119746},
{"learn":[2.48949562],"iteration":637,"passed_time":6.697042547,"remaining_time":3.799889345},
{"learn":[2.489108975],"iteration":638,"passed_time":6.707779965,"remaining_time":3.789528274},
{"learn":[2.48873709],"iteration":639,"passed_time":6.718692099,"remaining_time":3.779264306},
{"learn":[2.488159062],"iteration":640,"passed_time":6.728305588,"remaining_time":3.768270992},
{"learn":[2.487702686],"iteration":641,"passed_time":6.73833544,"remaining_time":3.757514155},
{"learn":[2.487138421],"iteration":642,"passed_time":6.749118726,"remaining_time":3.747177893},
{"learn":[2.486674192],"iteration":643,"passed_time":6.760136644,"remaining_time":3.736969946},
{"learn":[2.486248573],"iteration":644,"passed_time":6.770100098,"remaining_time":3.726179124},
{"learn":[2.485827471],"iteration":645,"passed_time":6.780053468,"remaining_time":3.715385337},
{"learn":[2.485309175],"iteration":646,"passed_time":6.790865406,"remaining_time":3.705062579},
{"learn":[2.484995852],"iteration":647,"passed_time":6.800971567,"remaining_time":3.694354925},
{"learn":[2.484609542],"iteration":648,"passed_time":6.811509634,"remaining_time":3.683882714},
{"learn":[2.484193614],"iteration":649,"passed_time":6.821667473,"remaining_time":3.673205563},
{"learn":[2.483837856],"iteration":650,"passed_time":6.831614071,"remaining_time":3.66241676},
{"learn":[2.483432453],"iteration":651,"passed_time":6.841700644,"remaining_time":3.651705252},
{"learn":[2.483031941],"iteration":652,"passed_time":6.851670756,"remaining_time":3.640933771},
{"learn":[2.482583135],"iteration":653,"passed_time":6.862176535,"remaining_time":3.630448136},
{"learn":[2.482177366],"iteration":654,"passed_time":6.872731961,"remaining_time":3.61998859},
{"learn":[2.481714835],"iteration":655,"passed_time":6.883753212,"remaining_time":3.609773026},
{"learn":[2.481376244],"iteration":656,"passed_time":6.893909332,"remaining_time":3.59910335},
{"learn":[2.480904244],"iteration":657,"passed_time":6.903701137,"remaining_time":3.58824588},
{"learn":[2.480460583],"iteration":658,"passed_time":6.913957688,"remaining_time":3.577632127},
{"learn":[2.480042131],"iteration":659,"passed_time":6.924928642,"remaining_time":3.567387482},
{"learn":[2.47961887],"iteration":660,"passed_time":6.935164269,"remaining_time":3.556763521},
{"learn":[2.479327944],"iteration":661,"passed_time":6.945538751,"remaining_time":3.546211628},
{"learn":[2.478911121],"iteration":662,"passed_time":6.955961143,"remaining_time":3.535684623},
{"learn":[2.478411505],"iteration":663,"passed_time":6.966836832,"remaining_time":3.525387313},
{"learn":[2.478029553],"iteration":664,"passed_time":6.97715973,"remaining_time":3.514809789},
{"learn":[2.477622747],"iteration":665,"passed_time":6.987889081,"remaining_time":3.504436866},
{"learn":[2.477123669],"iteration":666,"passed_time":6.999010305,"remaining_time":3.494258518},
{"learn":[2.47676058],"iteration":667,"passed_time":7.008313315,"remaining_time":3.483173683},
{"learn":[2.476376228],"iteration":668,"passed_time":7.018904368,"remaining_time":3.472731459},
{"learn":[2.47584726],"iteration":669,"passed_time":7.030413843,"remaining_time":3.462741147},
{"learn":[2.475397766],"iteration":670,"passed_time":7.040724562,"remaining_time":3.452158541},
{"learn":[2.474985204],"iteration":671,"passed_time":7.051467381,"remaining_time":3.44178765},
{"learn":[2.474557632],"iteration":672,"passed_time":7.062052591,"remaining_time":3.431339075},
{"learn":[2.474121373],"iteration":673,"passed_time":7.073108752,"remaining_time":3.421117883},
{"learn":[2.473801584],"iteration":674,"passed_time":7.083279004,"remaining_time":3.410467669},
{"learn":[2.473438144],"iteration":675,"passed_time":7.093480453,"remaining_time":3.399833826},
{"learn":[2.473021549],"iteration":676,"passed_time":7.104278552,"remaining_time":3.389485926},
{"learn":[2.472542669],"iteration":677,"passed_time":7.115324675,"remaining_time":3.379254492},
{"learn":[2.472172778],"iteration":678,"passed_time":7.125591173,"remaining_time":3.368652086},
{"learn":[2.471692128],"iteration":679,"passed_time":7.136274293,"remaining_time":3.358246726},
{"learn":[2.471174182],"iteration":680,"passed_time":7.147241719,"remaining_time":3.347973727},
{"learn":[2.470764204],"iteration":681,"passed_time":7.157830304,"remaining_time":3.337522048},
{"learn":[2.470294538],"iteration":682,"passed_time":7.169300323,"remaining_time":3.327479066},
{"learn":[2.469859563],"iteration":683,"passed_time":7.179608953,"remaining_time":3.316895364},
{"learn":[2.469487121],"iteration":684,"passed_time":7.189612247,"remaining_time":3.306172055},
{"learn":[2.469034894],"iteration":685,"passed_time":7.199386167,"remaining_time":3.295345855},
{"learn":[2.468614556],"iteration":686,"passed_time":7.209880605,"remaining_time":3.284850989},
{"learn":[2.468264727],"iteration":687,"passed_time":7.220604241,"remaining_time":3.274460063},
{"learn":[2.467745395],"iteration":688,"passed_time":7.231250142,"remaining_time":3.264033083},
{"learn":[2.467416924],"iteration":689,"passed_time":7.240964309,"remaining_time":3.253186863},
{"learn":[2.466854409],"iteration":690,"passed_time":7.252265803,"remaining_time":3.243053738},
{"learn":[2.466342294],"iteration":691,"passed_time":7.263024993,"remaining_time":3.232675864},
{"learn":[2.466110653],"iteration":692,"passed_time":7.273326775,"remaining_time":3.222094257},
{"learn":[2.465678179],"iteration":693,"passed_time":7.283271292,"remaining_time":3.21135593},
{"learn":[2.465324934],"iteration":694,"passed_time":7.293724415,"remaining_time":3.200843089},
{"learn":[2.464800038],"iteration":695,"passed_time":7.304520851,"remaining_time":3.190480372},
{"learn":[2.464286767],"iteration":696,"passed_time":7.315186537,"remaining_time":3.180059571},
{"learn":[2.464028996],"iteration":697,"passed_time":7.32493287,"remaining_time":3.169240296},
{"learn":[2.463483965],"iteration":698,"passed_time":7.335412566,"remaining_time":3.158739889},
{"learn":[2.463022511],"iteration":699,"passed_time":7.345852655,"remaining_time":3.148222566},
{"learn":[2.462509772],"iteration":700,"passed_time":7.356065182,"remaining_time":3.137608401},
{"learn":[2.462250657],"iteration":701,"passed_time":7.366089137,"remaining_time":3.126915332},
{"learn":[2.461764434],"iteration":702,"passed_time":7.376989888,"remaining_time":3.11659459},
{"learn":[2.461324177],"iteration":703,"passed_time":7.387411438,"remaining_time":3.106070718},
{"learn":[2.460996043],"iteration":704,"passed_time":7.397716671,"remaining_time":3.095498465},
{"learn":[2.46038889],"iteration":705,"passed_time":7.408446809,"remaining_time":3.085103912},
{"learn":[2.45985652],"iteration":706,"passed_time":7.419260208,"remaining_time":3.074742915},
{"learn":[2.459460437],"iteration":707,"passed_time":7.429756335,"remaining_time":3.064249788},
{"learn":[2.459060502],"iteration":708,"passed_time":7.439927212,"remaining_time":3.053623157},
{"learn":[2.45858234],"iteration":709,"passed_time":7.450469273,"remaining_time":3.043149421},
{"learn":[2.45825057],"iteration":710,"passed_time":7.460420823,"remaining_time":3.032435468},
{"learn":[2.4576996],"iteration":711,"passed_time":7.470832559,"remaining_time":3.021909799},
{"learn":[2.457287719],"iteration":712,"passed_time":7.481141826,"remaining_time":3.011343203},
{"learn":[2.456962971],"iteration":713,"passed_time":7.492058061,"remaining_time":3.001020456},
{"learn":[2.456481746],"iteration":714,"passed_time":7.502992159,"remaining_time":2.990703168},
{"learn":[2.456054901],"iteration":715,"passed_time":7.513707696,"remaining_time":2.980297466},
{"learn":[2.455632053],"iteration":716,"passed_time":7.523973325,"remaining_time":2.969713321},
{"learn":[2.455137823],"iteration":717,"passed_time":7.534398999,"remaining_time":2.959192922},
{"learn":[2.454844614],"iteration":718,"passed_time":7.545720563,"remaining_time":2.949022918},
{"learn":[2.45446107],"iteration":719,"passed_time":7.556202316,"remaining_time":2.938523123},
{"learn":[2.453942259],"iteration":720,"passed_time":7.567507707,"remaining_time":2.928342095},
{"learn":[2.4535232],"iteration":721,"passed_time":7.578697036,"remaining_time":2.918113263},
{"learn":[2.453144659],"iteration":722,"passed_time":7.588800381,"remaining_time":2.907465706},
{"learn":[2.452844666],"iteration":723,"passed_time":7.598907558,"remaining_time":2.896821113},
{"learn":[2.452585359],"iteration":724,"passed_time":7.615471187,"remaining_time":2.888627002},
{"learn":[2.452155903],"iteration":725,"passed_time":7.627618395,"remaining_time":2.87874303},
{"learn":[2.45182404],"iteration":726,"passed_time":7.637766126,"remaining_time":2.868101998},
{"learn":[2.451384383],"iteration":727,"passed_time":7.648197355,"remaining_time":2.857568242},
{"learn":[2.450993432],"iteration":728,"passed_time":7.659086708,"remaining_time":2.847205072},
{"learn":[2.450457898],"iteration":729,"passed_time":7.669679203,"remaining_time":2.836730664},
{"learn":[2.450021555],"iteration":730,"passed_time":7.680001482,"remaining_time":2.826156496},
{"learn":[2.449542039],"iteration":731,"passed_time":7.690787753,"remaining_time":2.815752893},
{"learn":[2.449210299],"iteration":732,"passed_time":7.701180032,"remaining_time":2.805204732},
{"learn":[2.449024738],"iteration":733,"passed_time":7.710821768,"remaining_time":2.794385001},
{"learn":[2.448575683],"iteration":734,"passed_time":7.720901313,"remaining_time":2.783726324},
{"learn":[2.448121828],"iteration":735,"passed_time":7.731538045,"remaining_time":2.773269081},
{"learn":[2.447694369],"iteration":736,"passed_time":7.741861219,"remaining_time":2.762699458},
{"learn":[2.447326741],"iteration":737,"passed_time":7.752365106,"remaining_time":2.752194658},
{"learn":[2.447044284],"iteration":738,"passed_time":7.762483949,"remaining_time":2.741553871},
{"learn":[2.446577228],"iteration":739,"passed_time":7.7725218,"remaining_time":2.730886038},
{"learn":[2.446212918],"iteration":740,"passed_time":7.78312935,"remaining_time":2.720419031},
{"learn":[2.445772908],"iteration":741,"passed_time":7.793858458,"remaining_time":2.709993911},
{"learn":[2.445475438],"iteration":742,"passed_time":7.803853746,"remaining_time":2.699314149},
{"learn":[2.445109114],"iteration":743,"passed_time":7.814038552,"remaining_time":2.688701437},
{"learn":[2.444717654],"iteration":744,"passed_time":7.824161822,"remaining_time":2.678068812},
{"learn":[2.444177004],"iteration":745,"passed_time":7.834522109,"remaining_time":2.667518252},
{"learn":[2.443791929],"iteration":746,"passed_time":7.845597731,"remaining_time":2.657210477},
{"learn":[2.443291568],"iteration":747,"passed_time":7.856979244,"remaining_time":2.647003702},
{"learn":[2.443048145],"iteration":748,"passed_time":7.866679687,"remaining_time":2.636230443},
{"learn":[2.442791628],"iteration":749,"passed_time":7.876855116,"remaining_time":2.625618372},
{"learn":[2.442358778],"iteration":750,"passed_time":7.886933759,"remaining_time":2.614975374},
{"learn":[2.441951298],"iteration":751,"passed_time":7.897659361,"remaining_time":2.604547236},
{"learn":[2.441598638],"iteration":752,"passed_time":7.907873121,"remaining_time":2.593950413},
{"learn":[2.441275504],"iteration":753,"passed_time":7.918379657,"remaining_time":2.583450127},
{"learn":[2.440886283],"iteration":754,"passed_time":7.928686648,"remaining_time":2.572885071},
{"learn":[2.440542006],"iteration":755,"passed_time":7.938780146,"remaining_time":2.562251793},
{"learn":[2.440142626],"iteration":756,"passed_time":7.949054583,"remaining_time":2.551678023},
{"learn":[2.439642811],"iteration":757,"passed_time":7.959706007,"remaining_time":2.541225401},
{"learn":[2.43933844],"iteration":758,"passed_time":7.970186038,"remaining_time":2.530717833},
{"learn":[2.439066929],"iteration":759,"passed_time":7.980773743,"remaining_time":2.52024434},
{"learn":[2.438718885],"iteration":760,"passed_time":7.992508032,"remaining_time":2.510130643},
{"learn":[2.438325585],"iteration":761,"passed_time":8.002847056,"remaining_time":2.499576902},
{"learn":[2.437961585],"iteration":762,"passed_time":8.012766816,"remaining_time":2.488893493},
{"learn":[2.437525284],"iteration":763,"passed_time":8.023063557,"remaining_time":2.478328533},
{"learn":[2.43719479],"iteration":764,"passed_time":8.033681691,"remaining_time":2.467863003},
{"learn":[2.436814282],"iteration":765,"passed_time":8.044142771,"remaining_time":2.457349097},
{"learn":[2.436422026],"iteration":766,"passed_time":8.054612803,"remaining_time":2.446838048},
{"learn":[2.436013354],"iteration":767,"passed_time":8.064890135,"remaining_time":2.436268895},
{"learn":[2.435599192],"iteration":768,"passed_time":8.075553853,"remaining_time":2.425816567},
{"learn":[2.435084045],"iteration":769,"passed_time":8.08619381,"remaining_time":2.415356592},
{"learn":[2.434644932],"iteration":770,"passed_time":8.096209818,"remaining_time":2.404710828},
{"learn":[2.434233487],"iteration":771,"passed_time":8.106231197,"remaining_time":2.394068281},
{"learn":[2.433756814],"iteration":772,"passed_time":8.116322644,"remaining_time":2.383447917},
{"learn":[2.433319635],"iteration":773,"passed_time":8.12703492,"remaining_time":2.373010196},
{"learn":[2.432983582],"iteration":774,"passed_time":8.136775394,"remaining_time":2.362289631},
{"learn":[2.432683831],"iteration":775,"passed_time":8.146844719,"remaining_time":2.351666517},
{"learn":[2.432376166],"iteration":776,"passed_time":8.15725884,"remaining_time":2.341143785},
{"learn":[2.431810472],"iteration":777,"passed_time":8.168540964,"remaining_time":2.330869015},
{"learn":[2.431507028],"iteration":778,"passed_time":8.17814771,"remaining_time":2.320116359},
{"learn":[2.431136029],"iteration":779,"passed_time":8.187793845,"remaining_time":2.309377751},
{"learn":[2.430725418],"iteration":780,"passed_time":8.197664475,"remaining_time":2.298704891},
{"learn":[2.430429166],"iteration":781,"passed_time":8.207488861,"remaining_time":2.288021191},
{"learn":[2.429971902],"iteration":782,"passed_time":8.21838365,"remaining_time":2.277636337},
{"learn":[2.429551871],"iteration":783,"passed_time":8.22874038,"remaining_time":2.267101941},
{"learn":[2.429122608],"iteration":784,"passed_time":8.239591854,"remaining_time":2.256703501},
{"learn":[2.42866234],"iteration":785,"passed_time":8.250589197,"remaining_time":2.246343624},
{"learn":[2.428210879],"iteration":786,"passed_time":8.261862348,"remaining_time":2.236056773},
{"learn":[2.427849398],"iteration":787,"passed_time":8.27236623,"remaining_time":2.225560458},
{"learn":[2.427300236],"iteration":788,"passed_time":8.282761553,"remaining_time":2.215035092},
{"learn":[2.427061186],"iteration":789,"passed_time":8.292848185,"remaining_time":2.204427999},
{"learn":[2.42661722],"iteration":790,"passed_time":8.303611313,"remaining_time":2.194000966},
{"learn":[2.426167752],"iteration":791,"passed_time":8.314442022,"remaining_time":2.183590834},
{"learn":[2.42567685],"iteration":792,"passed_time":8.325271568,"remaining_time":2.173179337},
{"learn":[2.425235735],"iteration":793,"passed_time":8.335761721,"remaining_time":2.162678734},
{"learn":[2.424847123],"iteration":794,"passed_time":8.345990896,"remaining_time":2.15211086},
{"learn":[2.424379543],"iteration":795,"passed_time":8.356938114,"remaining_time":2.141727858},
{"learn":[2.423947969],"iteration":796,"passed_time":8.367528789,"remaining_time":2.131252628},
{"learn":[2.423571337],"iteration":797,"passed_time":8.378267932,"remaining_time":2.120814689},
{"learn":[2.423179734],"iteration":798,"passed_time":8.388519794,"remaining_time":2.110253415},
{"learn":[2.422933435],"iteration":799,"passed_time":8.398363443,"remaining_time":2.099590861},
{"learn":[2.422604773],"iteration":800,"passed_time":8.408318385,"remaining_time":2.088958001},
{"learn":[2.422328567],"iteration":801,"passed_time":8.418789082,"remaining_time":2.078454162},
{"learn":[2.421983383],"iteration":802,"passed_time":8.428704757,"remaining_time":2.067814243},
{"learn":[2.421574138],"iteration":803,"passed_time":8.438976454,"remaining_time":2.057262917},
{"learn":[2.421219184],"iteration":804,"passed_time":8.449169128,"remaining_time":2.046693143},
{"learn":[2.420726482],"iteration":805,"passed_time":8.459692661,"remaining_time":2.036203941},
{"learn":[2.420311413],"iteration":806,"passed_time":8.470663804,"remaining_time":2.025821703},
{"learn":[2.41989115],"iteration":807,"passed_time":8.480694579,"remaining_time":2.015214553},
{"learn":[2.419544512],"iteration":808,"passed_time":8.490514726,"remaining_time":2.004559101},
{"learn":[2.419096891],"iteration":809,"passed_time":8.502017078,"remaining_time":1.994300302},
{"learn":[2.418867769],"iteration":810,"passed_time":8.511691541,"remaining_time":1.983612455},
{"learn":[2.418355285],"iteration":811,"passed_time":8.522489096,"remaining_time":1.973187131},
{"learn":[2.4180776],"iteration":812,"passed_time":8.533144474,"remaining_time":1.962728188},
{"learn":[2.417677931],"iteration":813,"passed_time":8.545040586,"remaining_time":1.952552271},
{"learn":[2.417397156],"iteration":814,"passed_time":8.555737448,"remaining_time":1.942099911},
{"learn":[2.417006401],"iteration":815,"passed_time":8.565554026,"remaining_time":1.931448457},
{"learn":[2.416738686],"iteration":816,"passed_time":8.576003465,"remaining_time":1.920940801},
{"learn":[2.416386937],"iteration":817,"passed_time":8.585956253,"remaining_time":1.910322785},
{"learn":[2.416032076],"iteration":818,"passed_time":8.596688881,"remaining_time":1.899878739},
{"learn":[2.415609219],"iteration":819,"passed_time":8.609106015,"remaining_time":1.889803759},
{"learn":[2.415245044],"iteration":820,"passed_time":8.619580075,"remaining_time":1.879299432},
{"learn":[2.414879192],"iteration":821,"passed_time":8.629626606,"remaining_time":1.868702598},
{"learn":[2.414588157],"iteration":822,"passed_time":8.640507309,"remaining_time":1.858286505},
{"learn":[2.41420443],"iteration":823,"passed_time":8.651062275,"remaining_time":1.847799709},
{"learn":[2.413744677],"iteration":824,"passed_time":8.662508333,"remaining_time":1.837501768},
{"learn":[2.413437484],"iteration":825,"passed_time":8.672776379,"remaining_time":1.826952893},
{"learn":[2.413156058],"iteration":826,"passed_time":8.682946157,"remaining_time":1.816384142},
{"learn":[2.412783215],"iteration":827,"passed_time":8.693534287,"remaining_time":1.805903258},
{"learn":[2.412394281],"iteration":828,"passed_time":8.703792148,"remaining_time":1.79535399},
{"learn":[2.412179061],"iteration":829,"passed_time":8.713593005,"remaining_time":1.78471182},
{"learn":[2.411756993],"iteration":830,"passed_time":8.724272168,"remaining_time":1.774250296},
{"learn":[2.411355884],"iteration":831,"passed_time":8.735282162,"remaining_time":1.763855052},
{"learn":[2.410947958],"iteration":832,"passed_time":8.745548742,"remaining_time":1.753309292},
{"learn":[2.410572844],"iteration":833,"passed_time":8.756017619,"remaining_time":1.742804466},
{"learn":[2.410144467],"iteration":834,"passed_time":8.766943821,"remaining_time":1.732390096},
{"learn":[2.409821077],"iteration":835,"passed_time":8.777209808,"remaining_time":1.721844986},
{"learn":[2.409317674],"iteration":836,"passed_time":8.788160351,"remaining_time":1.711433856},
{"learn":[2.408873366],"iteration":837,"passed_time":8.799179608,"remaining_time":1.701034721},
{"learn":[2.408494679],"iteration":838,"passed_time":8.809765801,"remaining_time":1.690551006},
{"learn":[2.408148593],"iteration":839,"passed_time":8.81972043,"remaining_time":1.679946749},
{"learn":[2.407644043],"iteration":840,"passed_time":8.83069119,"remaining_time":1.669536146},
{"learn":[2.407295323],"iteration":841,"passed_time":8.841305868,"remaining_time":1.659057396},
{"learn":[2.406863073],"iteration":842,"passed_time":8.851740631,"remaining_time":1.648544815},
{"learn":[2.406462225],"iteration":843,"passed_time":8.861793163,"remaining_time":1.63796177},
{"learn":[2.405967659],"iteration":844,"passed_time":8.87285312,"remaining_time":1.627564774},
{"learn":[2.4056721],"iteration":845,"passed_time":8.883012376,"remaining_time":1.617002253},
{"learn":[2.405231697],"iteration":846,"passed_time":8.893449737,"remaining_time":1.606490921},
{"learn":[2.404909118],"iteration":847,"passed_time":8.903641301,"remaining_time":1.595935705},
{"learn":[2.404444795],"iteration":848,"passed_time":8.915087869,"remaining_time":1.585604556},
{"learn":[2.404186206],"iteration":849,"passed_time":8.925034917,"remaining_time":1.575006162},
{"learn":[2.403714387],"iteration":850,"passed_time":8.93565892,"remaining_time":1.564527825},
{"learn":[2.403343349],"iteration":851,"passed_time":8.946480894,"remaining_time":1.554083536},
{"learn":[2.402992077],"iteration":852,"passed_time":8.95669016,"remaining_time":1.543532771},
{"learn":[2.402435432],"iteration":853,"passed_time":8.967772641,"remaining_time":1.533132091},
{"learn":[2.402028704],"iteration":854,"passed_time":8.97765105,"remaining_time":1.522525617},
{"learn":[2.401618841],"iteration":855,"passed_time":8.989174947,"remaining_time":1.512197655},
{"learn":[2.40111386],"iteration":856,"passed_time":8.999944999,"remaining_time":1.501741114},
{"learn":[2.400710634],"iteration":857,"passed_time":9.010176813,"remaining_time":1.491194764},
{"learn":[2.400084539],"iteration":858,"passed_time":9.020891668,"remaining_time":1.480728434},
{"learn":[2.399744266],"iteration":859,"passed_time":9.031673513,"remaining_time":1.470272432},
{"learn":[2.399533666],"iteration":860,"passed_time":9.041496951,"remaining_time":1.459660948},
{"learn":[2.399158407],"iteration":861,"passed_time":9.051725141,"remaining_time":1.44911609},
{"learn":[2.398807638],"iteration":862,"passed_time":9.062045426,"remaining_time":1.438586586},
{"learn":[2.398507957],"iteration":863,"passed_time":9.072866186,"remaining_time":1.428136344},
{"learn":[2.398100408],"iteration":864,"passed_time":9.08737769,"remaining_time":1.418261258},
{"learn":[2.397695441],"iteration":865,"passed_time":9.097766749,"remaining_time":1.40773758},
{"learn":[2.397375418],"iteration":866,"passed_time":9.108711988,"remaining_time":1.397299532},
{"learn":[2.39711941],"iteration":867,"passed_time":9.118424956,"remaining_time":1.38667292},
{"learn":[2.396771983],"iteration":868,"passed_time":9.128801498,"remaining_time":1.376148442},
{"learn":[2.396527726],"iteration":869,"passed_time":9.139172188,"remaining_time":1.36562343},
{"learn":[2.396295616],"iteration":870,"passed_time":9.149286722,"remaining_time":1.355060835},
{"learn":[2.395741242],"iteration":871,"passed_time":9.160808474,"remaining_time":1.344705831},
{"learn":[2.395256864],"iteration":872,"passed_time":9.171612711,"remaining_time":1.334243774},
{"learn":[2.394961222],"iteration":873,"passed_time":9.181380856,"remaining_time":1.323631565},
{"learn":[2.394704546],"iteration":874,"passed_time":9.191345687,"remaining_time":1.313049384},
{"learn":[2.394140532],"iteration":875,"passed_time":9.202165208,"remaining_time":1.302589596},
{"learn":[2.393891661],"iteration":876,"passed_time":9.211799549,"remaining_time":1.291962765},
{"learn":[2.393635311],"iteration":877,"passed_time":9.221946487,"remaining_time":1.281409421},
{"learn":[2.393200384],"iteration":878,"passed_time":9.233907352,"remaining_time":1.2711067},
{"learn":[2.392706062],"iteration":879,"passed_time":9.244584748,"remaining_time":1.260625193},
{"learn":[2.392291291],"iteration":880,"passed_time":9.255112494,"remaining_time":1.250123027},
{"learn":[2.391875558],"iteration":881,"passed_time":9.26593859,"remaining_time":1.239660718},
{"learn":[2.39154682],"iteration":882,"passed_time":9.276870873,"remaining_time":1.229211656},
{"learn":[2.391077104],"iteration":883,"passed_time":9.287218392,"remaining_time":1.218684766},
{"learn":[2.390646207],"iteration":884,"passed_time":9.297871393,"remaining_time":1.208197978},
{"learn":[2.390302288],"iteration":885,"passed_time":9.307947155,"remaining_time":1.197636541},
{"learn":[2.389862309],"iteration":886,"passed_time":9.318202977,"remaining_time":1.187099139},
{"learn":[2.389604708],"iteration":887,"passed_time":9.328913415,"remaining_time":1.17661971},
{"learn":[2.38928876],"iteration":888,"passed_time":9.33941216,"remaining_time":1.166113329},
{"learn":[2.388957185],"iteration":889,"passed_time":9.349234193,"remaining_time":1.155523327},
{"learn":[2.388597373],"iteration":890,"passed_time":9.359585156,"remaining_time":1.144999755},
{"learn":[2.388187371],"iteration":891,"passed_time":9.370577995,"remaining_time":1.134554286},
{"learn":[2.387743255],"iteration":892,"passed_time":9.380993989,"remaining_time":1.124038473},
{"learn":[2.387360757],"iteration":893,"passed_time":9.391840227,"remaining_time":1.113573897},
{"learn":[2.386962997],"iteration":894,"passed_time":9.401819418,"remaining_time":1.103006747},
{"learn":[2.386573695],"iteration":895,"passed_time":9.411681024,"remaining_time":1.092427262},
{"learn":[2.386255219],"iteration":896,"passed_time":9.422208227,"remaining_time":1.081925805},
{"learn":[2.385813545],"iteration":897,"passed_time":9.433225622,"remaining_time":1.07147997},
{"learn":[2.385460479],"iteration":898,"passed_time":9.443264543,"remaining_time":1.060922935},
{"learn":[2.38515541],"iteration":899,"passed_time":9.454331175,"remaining_time":1.050481242},
{"learn":[2.384885472],"iteration":900,"passed_time":9.46457331,"remaining_time":1.039947567},
{"learn":[2.384542973],"iteration":901,"passed_time":9.474401562,"remaining_time":1.029369571},
{"learn":[2.384159795],"iteration":902,"passed_time":9.485388761,"remaining_time":1.01891773},
{"learn":[2.383787718],"iteration":903,"passed_time":9.495349599,"remaining_time":1.00835571},
{"learn":[2.383380717],"iteration":904,"passed_time":9.506125639,"remaining_time":0.9978805919},
{"learn":[2.382964143],"iteration":905,"passed_time":9.516281939,"remaining_time":0.9873405102},
{"learn":[2.382702422],"iteration":906,"passed_time":9.527182195,"remaining_time":0.976877557},
{"learn":[2.3824577],"iteration":907,"passed_time":9.536895979,"remaining_time":0.9662934252},
{"learn":[2.382051224],"iteration":908,"passed_time":9.548627874,"remaining_time":0.9559132416},
{"learn":[2.381680737],"iteration":909,"passed_time":9.558950319,"remaining_time":0.9453906909},
{"learn":[2.381295659],"iteration":910,"passed_time":9.569500125,"remaining_time":0.9348907916},
{"learn":[2.380810031],"iteration":911,"passed_time":9.580097455,"remaining_time":0.9243953685},
{"learn":[2.380357822],"iteration":912,"passed_time":9.591085539,"remaining_time":0.9139369572},
{"learn":[2.379953829],"iteration":913,"passed_time":9.601394625,"remaining_time":0.9034134986},
{"learn":[2.379671419],"iteration":914,"passed_time":9.611232877,"remaining_time":0.89284677},
{"learn":[2.379205068],"iteration":915,"passed_time":9.621626645,"remaining_time":0.8823325744},
{"learn":[2.378867845],"iteration":916,"passed_time":9.63199061,"remaining_time":0.871815944},
{"learn":[2.378450753],"iteration":917,"passed_time":9.642566099,"remaining_time":0.8613185404},
{"learn":[2.378199937],"iteration":918,"passed_time":9.652862051,"remaining_time":0.8507963288},
{"learn":[2.377885245],"iteration":919,"passed_time":9.663680306,"remaining_time":0.8403200266},
{"learn":[2.377560738],"iteration":920,"passed_time":9.673883122,"remaining_time":0.8297901918},
{"learn":[2.377166941],"iteration":921,"passed_time":9.684143863,"remaining_time":0.8192659667},
{"learn":[2.376837244],"iteration":922,"passed_time":9.693957545,"remaining_time":0.8087050173},
{"learn":[2.376658594],"iteration":923,"passed_time":9.703584843,"remaining_time":0.7981303551},
{"learn":[2.376262674],"iteration":924,"passed_time":9.713729068,"remaining_time":0.7875996542},
{"learn":[2.375847623],"iteration":925,"passed_time":9.724342429,"remaining_time":0.7771072783},
{"learn":[2.375441222],"iteration":926,"passed_time":9.734951662,"remaining_time":0.7666143164},
{"learn":[2.375003731],"iteration":927,"passed_time":9.745872336,"remaining_time":0.7561452674},
{"learn":[2.374641844],"iteration":928,"passed_time":9.755982579,"remaining_time":0.745613308},
{"learn":[2.374328902],"iteration":929,"passed_time":9.76614768,"remaining_time":0.7350863845},
{"learn":[2.3739069],"iteration":930,"passed_time":9.776476539,"remaining_time":0.7245723751},
{"learn":[2.373565041],"iteration":931,"passed_time":9.787197167,"remaining_time":0.7140873469},
{"learn":[2.373206946],"iteration":932,"passed_time":9.797654375,"remaining_time":0.7035828973},
{"learn":[2.372951897],"iteration":933,"passed_time":9.807664957,"remaining_time":0.6930469884},
{"learn":[2.372424941],"iteration":934,"passed_time":9.818351407,"remaining_time":0.6825591887},
{"learn":[2.371982561],"iteration":935,"passed_time":9.828887662,"remaining_time":0.6720606949},
{"learn":[2.371651114],"iteration":936,"passed_time":9.839107353,"remaining_time":0.6615408359},
{"learn":[2.371226915],"iteration":937,"passed_time":9.849343227,"remaining_time":0.6510226867},
{"learn":[2.370835568],"iteration":938,"passed_time":9.860085426,"remaining_time":0.6405380309},
{"learn":[2.370557207],"iteration":939,"passed_time":9.870769753,"remaining_time":0.6300491332},
{"learn":[2.370252212],"iteration":940,"passed_time":9.881516168,"remaining_time":0.619563713},
{"learn":[2.370000559],"iteration":941,"passed_time":9.891397596,"remaining_time":0.6090244805},
{"learn":[2.369647722],"iteration":942,"passed_time":9.901547745,"remaining_time":0.598502886},
{"learn":[2.369246203],"iteration":943,"passed_time":9.911904877,"remaining_time":0.5879943571},
{"learn":[2.368834908],"iteration":944,"passed_time":9.922379849,"remaining_time":0.5774930071},
{"learn":[2.36856102],"iteration":945,"passed_time":9.932735358,"remaining_time":0.5669848936},
{"learn":[2.368232937],"iteration":946,"passed_time":9.943012615,"remaining_time":0.5564727229},
{"learn":[2.36791365],"iteration":947,"passed_time":9.953307998,"remaining_time":0.5459620421},
{"learn":[2.367565752],"iteration":948,"passed_time":9.96370998,"remaining_time":0.5354575437},
{"learn":[2.367228503],"iteration":949,"passed_time":9.974234573,"remaining_time":0.5249597144},
{"learn":[2.366831633],"iteration":950,"passed_time":9.984662182,"remaining_time":0.5144568317},
{"learn":[2.366361623],"iteration":951,"passed_time":9.995763566,"remaining_time":0.503988079},
{"learn":[2.366005594],"iteration":952,"passed_time":10.00621436,"remaining_time":0.4934859128},
{"learn":[2.365694839],"iteration":953,"passed_time":10.0162325,"remaining_time":0.4829629929},
{"learn":[2.365380289],"iteration":954,"passed_time":10.02770398,"remaining_time":0.4725096114},
{"learn":[2.364931627],"iteration":955,"passed_time":10.03845367,"remaining_time":0.4620208801},
{"learn":[2.364650031],"iteration":956,"passed_time":10.04832726,"remaining_time":0.4514922384},
{"learn":[2.36420026],"iteration":957,"passed_time":10.05976583,"remaining_time":0.441033575},
{"learn":[2.363862999],"iteration":958,"passed_time":10.07028053,"remaining_time":0.4305333701},
{"learn":[2.363585009],"iteration":959,"passed_time":10.08021451,"remaining_time":0.420008938},
{"learn":[2.363247388],"iteration":960,"passed_time":10.0908527,"remaining_time":0.4095143134},
{"learn":[2.362823835],"iteration":961,"passed_time":10.10186877,"remaining_time":0.3990343175},
{"learn":[2.362417295],"iteration":962,"passed_time":10.11183717,"remaining_time":0.3885129547},
{"learn":[2.361905549],"iteration":963,"passed_time":10.12217582,"remaining_time":0.3780065658},
{"learn":[2.361639923],"iteration":964,"passed_time":10.13244476,"remaining_time":0.3674979966},
{"learn":[2.361260269],"iteration":965,"passed_time":10.14273908,"remaining_time":0.3569908164},
{"learn":[2.360892876],"iteration":966,"passed_time":10.15308586,"remaining_time":0.3464858671},
{"learn":[2.360490002],"iteration":967,"passed_time":10.16380403,"remaining_time":0.3359935218},
{"learn":[2.360087256],"iteration":968,"passed_time":10.17348442,"remaining_time":0.3254675097},
{"learn":[2.359704608],"iteration":969,"passed_time":10.18358893,"remaining_time":0.3149563587},
{"learn":[2.359340571],"iteration":970,"passed_time":10.19405981,"remaining_time":0.3044569871},
{"learn":[2.359008078],"iteration":971,"passed_time":10.20402046,"remaining_time":0.2939429762},
{"learn":[2.358541021],"iteration":972,"passed_time":10.2149611,"remaining_time":0.2834572966},
{"learn":[2.358216493],"iteration":973,"passed_time":10.22547593,"remaining_time":0.2729593164},
{"learn":[2.357919499],"iteration":974,"passed_time":10.23513264,"remaining_time":0.2624392986},
{"learn":[2.357552734],"iteration":975,"passed_time":10.24680102,"remaining_time":0.2519705169},
{"learn":[2.357338758],"iteration":976,"passed_time":10.25655305,"remaining_time":0.241454166},
{"learn":[2.357029518],"iteration":977,"passed_time":10.26660706,"remaining_time":0.2309461711},
{"learn":[2.356635632],"iteration":978,"passed_time":10.27733645,"remaining_time":0.2204535908},
{"learn":[2.356300472],"iteration":979,"passed_time":10.28813818,"remaining_time":0.2099620037},
{"learn":[2.355966464],"iteration":980,"passed_time":10.29846418,"remaining_time":0.1994605702},
{"learn":[2.355654102],"iteration":981,"passed_time":10.30935174,"remaining_time":0.1889697876},
{"learn":[2.355294882],"iteration":982,"passed_time":10.31973321,"remaining_time":0.1784694451},
{"learn":[2.3548742],"iteration":983,"passed_time":10.33031345,"remaining_time":0.1679725764},
{"learn":[2.354494334],"iteration":984,"passed_time":10.34050114,"remaining_time":0.1574695605},
{"learn":[2.3541397],"iteration":985,"passed_time":10.35117349,"remaining_time":0.1469740657},
{"learn":[2.353850017],"iteration":986,"passed_time":10.3611411,"remaining_time":0.1364689304},
{"learn":[2.353450074],"iteration":987,"passed_time":10.37150574,"remaining_time":0.1259697053},
{"learn":[2.353165174],"iteration":988,"passed_time":10.38215655,"remaining_time":0.1154739353},
{"learn":[2.352728915],"iteration":989,"passed_time":10.39310387,"remaining_time":0.1049808471},
{"learn":[2.352359497],"iteration":990,"passed_time":10.4037686,"remaining_time":0.09448427585},
{"learn":[2.352013445],"iteration":991,"passed_time":10.41483605,"remaining_time":0.0839906133},
{"learn":[2.351695203],"iteration":992,"passed_time":10.4253323,"remaining_time":0.07349176848},
{"learn":[2.351480924],"iteration":993,"passed_time":10.43516495,"remaining_time":0.06298892325},
{"learn":[2.351055745],"iteration":994,"passed_time":10.44616205,"remaining_time":0.05249327664},
{"learn":[2.350698706],"iteration":995,"passed_time":10.45693172,"remaining_time":0.0419957097},
{"learn":[2.350366909],"iteration":996,"passed_time":10.46730137,"remaining_time":0.0314963933},
{"learn":[2.349982128],"iteration":997,"passed_time":10.47797429,"remaining_time":0.02099794448},
{"learn":[2.349649084],"iteration":998,"passed_time":10.48819552,"remaining_time":0.01049869421},
{"learn":[2.349406657],"iteration":999,"passed_time":10.4985674,"remaining_time":0}
]}